[
  {
    "id": "knowledge.acquisition.mod.mischief-8a5fc526",
    "kind": "knowledge",
    "module": "acquisition",
    "title": "顽皮",
    "subject": {
      "canonical": "Mischief",
      "displayName": "顽皮",
      "category": "mod",
      "categoryRefs": [
        "companionmod",
        "standardmod"
      ]
    },
    "officialUniqueName": "/Lotus/Types/Friendly/Pets/CatbrowPetPrecepts/CatbrowDistractPrecept",
    "maxRank": 3,
    "effectDetails": [
      "笑面型库娃每过 7 秒，便能进入隐身状态 9 秒，同时放出拥有 15% 回避几率的诱饵库娃来吸引火力并在死亡时致盲附近的敌人。"
    ],
    "rarity": "Rare",
    "polarity": "penjaga",
    "tradable": true,
    "prerequisites": [],
    "tips": [],
    "tipKeywords": [
      "本质机制",
      "具体计算公式",
      "加成层级",
      "与同类效果的叠加方式",
      "适用限制"
    ],
    "methodRefs": [],
    "acquisitionStatus": "complete",
    "sources": [
      {
        "url": "https://wiki.warframe.com/w/Mischief",
        "label": "Warframe Wiki - Mischief"
      }
    ],
    "gameVersion": "warframe-items@1.1269.87",
    "updatedAt": "2026-07-17",
    "reviewStatus": "draft",
    "reviewedBy": [],
    "tags": [
      "acquisition",
      "mod",
      "standard-mod",
      "companion-mod"
    ],
    "generator": {
      "name": "sync-mods",
      "version": 4
    },
    "modAcquisition": {
      "generated": {
        "identity": {
          "officialUniqueName": "/Lotus/Types/Friendly/Pets/CatbrowPetPrecepts/CatbrowDistractPrecept",
          "canonical": "Mischief",
          "displayName": "顽皮",
          "maxRank": 3,
          "variant": "standard",
          "typeFolder": "companion"
        },
        "wiki": {
          "wiki": {
            "pageTitle": "Mischief",
            "pageId": 1016794,
            "revisionId": 2696205,
            "pageTimestamp": "2025-09-01T14:48:02Z",
            "compiledAt": "2026-07-17T01:48:33.764Z",
            "sourceDatabase": {
              "sha256": "861480127CC518FC3CCA9B28334AEEC16AB8AEA383D08EA5D3B55B701DA475B9",
              "size": 2322874368
            }
          },
          "methods": [
            {
              "type": "companion-included",
              "sourceItemCanonical": "Smeeta Kavat",
              "chance": null,
              "quantity": 1,
              "availability": "guaranteed-when-requirements-met",
              "reviewStatus": "draft",
              "provenance": {
                "source": "local-wiki-sqlite",
                "pageTitle": "Mischief",
                "pageId": 1016794,
                "revisionId": 2696205,
                "section": "Acquisition",
                "excerpt": "Mischief is automatically acquired upon obtaining a Smeeta Kavat ."
              }
            }
          ],
          "evidence": [
            {
              "type": "acquisition-prose",
              "reviewStatus": "draft",
              "provenance": {
                "source": "local-wiki-sqlite",
                "pageTitle": "Mischief",
                "pageId": 1016794,
                "revisionId": 2696205,
                "section": "Acquisition",
                "excerpt": "Mischief is automatically acquired upon obtaining a Smeeta Kavat ."
              }
            }
          ],
          "mechanicsEvidence": {
            "status": "draft",
            "notes": [
              {
                "reviewStatus": "draft",
                "provenance": {
                  "source": "local-wiki-sqlite",
                  "pageTitle": "Mischief",
                  "pageId": 1016794,
                  "revisionId": 2696205,
                  "section": "Notes",
                  "excerpt": "The Smeeta Kavat can attack while cloaked and remain cloaked, allowing them to execute several attacks while invisible."
                }
              },
              {
                "reviewStatus": "draft",
                "provenance": {
                  "source": "local-wiki-sqlite",
                  "pageTitle": "Mischief",
                  "pageId": 1016794,
                  "revisionId": 2696205,
                  "section": "Notes",
                  "excerpt": "Decoy possesses 50% of the Smeeta's Health , with 100% Critical Chance and 2.0x Critical Multiplier ."
                }
              },
              {
                "reviewStatus": "draft",
                "provenance": {
                  "source": "local-wiki-sqlite",
                  "pageTitle": "Mischief",
                  "pageId": 1016794,
                  "revisionId": 2696205,
                  "section": "Notes",
                  "excerpt": "As long as the decoy is active, the Smeeta Kavat is invisible and invulnerable. If the decoy dies, both effects will end."
                }
              },
              {
                "reviewStatus": "draft",
                "provenance": {
                  "source": "local-wiki-sqlite",
                  "pageTitle": "Mischief",
                  "pageId": 1016794,
                  "revisionId": 2696205,
                  "section": "Notes",
                  "excerpt": "Blind has a radius of 8 meters."
                }
              },
              {
                "reviewStatus": "draft",
                "provenance": {
                  "source": "local-wiki-sqlite",
                  "pageTitle": "Mischief",
                  "pageId": 1016794,
                  "revisionId": 2696205,
                  "section": "Notes",
                  "excerpt": "The decoy can be targeted by a Limbo 's Banish , which can allow it to draw much more fire from enemies for it's duration. Note that no matter what plane the Smeeta Kavat is in, the decoy will always spawn in the material plane."
                }
              }
            ],
            "usage": []
          },
          "unresolvedEntities": [],
          "status": "complete"
        },
        "officialDrops": [
          {
            "type": "official-drop",
            "sourceCanonical": "Kavat",
            "chance": 0.0083,
            "quantity": 1,
            "rarity": "Rare",
            "reviewStatus": "draft",
            "provenance": {
              "source": "warframe-items",
              "input": "Mods.json",
              "officialUniqueName": "/Lotus/Types/Friendly/Pets/CatbrowPetPrecepts/CatbrowDistractPrecept"
            }
          }
        ]
      },
      "manual": {
        "methods": [],
        "methodRefs": [],
        "overrides": {},
        "reviewStatus": "draft",
        "reviewedBy": []
      }
    }
  }
]
