[
  {
    "id": "knowledge.acquisition.mod.stalk-ffc350a9",
    "kind": "knowledge",
    "module": "acquisition",
    "title": "隐密追踪",
    "subject": {
      "canonical": "Stalk",
      "displayName": "隐密追踪",
      "category": "mod",
      "categoryRefs": [
        "companionmod",
        "standardmod"
      ]
    },
    "officialUniqueName": "/Lotus/Types/Friendly/Pets/KubrowPetPrecepts/KubrowCloakPrecept",
    "maxRank": 5,
    "effectDetails": [
      "当距离敌人24 米范围内时，库狛与其主人一起进入潜行状态以悄悄接近猎物。"
    ],
    "rarity": "Rare",
    "polarity": "penjaga",
    "tradable": true,
    "prerequisites": [],
    "tips": [],
    "tipKeywords": [
      "本质机制",
      "具体计算公式",
      "加成层级",
      "与同类效果的叠加方式",
      "适用限制"
    ],
    "methodRefs": [],
    "acquisitionStatus": "stub",
    "sources": [
      {
        "url": "https://wiki.warframe.com/w/Stalk",
        "label": "Warframe Wiki - Stalk"
      }
    ],
    "gameVersion": "warframe-items@1.1269.87",
    "updatedAt": "2026-07-14",
    "reviewStatus": "draft",
    "reviewedBy": [],
    "tags": [
      "acquisition",
      "mod",
      "standard-mod",
      "companion-mod"
    ],
    "generator": {
      "name": "sync-mods",
      "version": 3
    },
    "modAcquisition": {
      "generated": {
        "identity": {
          "officialUniqueName": "/Lotus/Types/Friendly/Pets/KubrowPetPrecepts/KubrowCloakPrecept",
          "canonical": "Stalk",
          "displayName": "隐密追踪",
          "maxRank": 5,
          "variant": "standard",
          "typeFolder": "companion"
        },
        "wiki": {
          "wiki": {
            "pageTitle": "Stalk",
            "pageId": 510271,
            "revisionId": 2744672,
            "pageTimestamp": "2026-03-22T00:34:19Z",
            "compiledAt": "2026-07-14T05:59:08.863Z",
            "sourceDatabase": {
              "sha256": "53869CC38887A16102730CA4E6D3F2F14F87E08171D1AFE3A2FFB4B5B7DFACF2",
              "size": 2317266944
            }
          },
          "methods": [],
          "evidence": [
            {
              "type": "acquisition-prose",
              "reviewStatus": "draft",
              "provenance": {
                "pageTitle": "Stalk",
                "pageId": 510271,
                "revisionId": 2744672,
                "section": "Acquisition",
                "excerpt": "Stalk is automatically acquired upon obtaining a Huras Kubrow ."
              }
            }
          ],
          "mechanicsEvidence": {
            "status": "draft",
            "notes": [
              {
                "reviewStatus": "draft",
                "provenance": {
                  "pageTitle": "Stalk",
                  "pageId": 510271,
                  "revisionId": 2744672,
                  "section": "Notes",
                  "excerpt": "When an enemy is within 24m of the Huras Kubrow, it will cloak both itself and its master with Invisibility ."
                }
              },
              {
                "reviewStatus": "draft",
                "provenance": {
                  "pageTitle": "Stalk",
                  "pageId": 510271,
                  "revisionId": 2744672,
                  "section": "Notes",
                  "excerpt": "Activation does not require line of sight from player or Huras Kubrow."
                }
              },
              {
                "reviewStatus": "draft",
                "provenance": {
                  "pageTitle": "Stalk",
                  "pageId": 510271,
                  "revisionId": 2744672,
                  "section": "Notes",
                  "excerpt": "The activation range of Stalk is centered on the Huras Kubrow, not the player."
                }
              },
              {
                "reviewStatus": "draft",
                "provenance": {
                  "pageTitle": "Stalk",
                  "pageId": 510271,
                  "revisionId": 2744672,
                  "section": "Notes",
                  "excerpt": "The Kubrow will make a howl animation when activating Stalk."
                }
              },
              {
                "reviewStatus": "draft",
                "provenance": {
                  "pageTitle": "Stalk",
                  "pageId": 510271,
                  "revisionId": 2744672,
                  "section": "Notes",
                  "excerpt": "Stalk lasts indefinitely until one of the following happens:"
                }
              },
              {
                "reviewStatus": "draft",
                "provenance": {
                  "pageTitle": "Stalk",
                  "pageId": 510271,
                  "revisionId": 2744672,
                  "section": "Notes",
                  "excerpt": "The player attacks with a weapon."
                }
              },
              {
                "reviewStatus": "draft",
                "provenance": {
                  "pageTitle": "Stalk",
                  "pageId": 510271,
                  "revisionId": 2744672,
                  "section": "Notes",
                  "excerpt": "Attacking with the Operator does not break the cloak."
                }
              },
              {
                "reviewStatus": "draft",
                "provenance": {
                  "pageTitle": "Stalk",
                  "pageId": 510271,
                  "revisionId": 2744672,
                  "section": "Notes",
                  "excerpt": "Codex Scanner and Synthesis Scanner are considered weapons."
                }
              },
              {
                "reviewStatus": "draft",
                "provenance": {
                  "pageTitle": "Stalk",
                  "pageId": 510271,
                  "revisionId": 2744672,
                  "section": "Notes",
                  "excerpt": "No enemies are within the detection range."
                }
              },
              {
                "reviewStatus": "draft",
                "provenance": {
                  "pageTitle": "Stalk",
                  "pageId": 510271,
                  "revisionId": 2744672,
                  "section": "Notes",
                  "excerpt": "Stalk will remain active for 3 seconds when enemies are no longer within range. Moving near enemies again will sustain it."
                }
              },
              {
                "reviewStatus": "draft",
                "provenance": {
                  "pageTitle": "Stalk",
                  "pageId": 510271,
                  "revisionId": 2744672,
                  "section": "Notes",
                  "excerpt": "The player is inactive for 1 minute."
                }
              },
              {
                "reviewStatus": "draft",
                "provenance": {
                  "pageTitle": "Stalk",
                  "pageId": 510271,
                  "revisionId": 2744672,
                  "section": "Notes",
                  "excerpt": "Has a 7 second cooldown after leaving any kind of invisibility, including itself."
                }
              },
              {
                "reviewStatus": "draft",
                "provenance": {
                  "pageTitle": "Stalk",
                  "pageId": 510271,
                  "revisionId": 2744672,
                  "section": "Notes",
                  "excerpt": "Activating other forms of invisibility while Stalk is active will not break the effect of Stalk after the other effect ends, provided there is still an enemy in proximity and no weapon/ability that would break the effect was used."
                }
              }
            ],
            "usage": []
          },
          "unresolvedEntities": [],
          "status": "unresolved"
        }
      },
      "manual": {
        "methods": [],
        "methodRefs": [],
        "overrides": {},
        "reviewStatus": "draft",
        "reviewedBy": []
      }
    }
  }
]
