{
  "id": "knowledge.acquisition.resource.travoride",
  "kind": "knowledge",
  "module": "acquisition",
  "title": "Travoride",
  "subject": {
    "canonical": "Travoride",
    "displayName": "铁镍矿",
    "category": "resource",
    "officialUniqueName": "/Lotus/Types/Items/Gems/Solaris/SolarisCommonOreAItem",
    "categoryRefs": [
      "resource-unresolved"
    ]
  },
  "prerequisites": [],
  "methodRefs": [],
  "resourceAcquisition": {
    "generated": {
      "officialUniqueName": "/Lotus/Types/Items/Gems/Solaris/SolarisCommonOreAItem",
      "canonical": "Travoride",
      "displayName": "铁镍矿",
      "localizationStatus": "official-zh",
      "semanticKinds": [
        "mineral"
      ],
      "evidence": [],
      "routing": {
        "category": "resource-unresolved",
        "variables": {
          "resourceName": "铁镍矿"
        },
        "status": "unresolved"
      }
    },
    "manual": {
      "tips": [],
      "tipKeywords": [],
      "routingOverride": null,
      "reviewedBy": []
    }
  },
  "sources": [
    {
      "url": "https://github.com/WFCD/warframe-items",
      "label": "warframe-items / Warframe Public Export"
    }
  ],
  "gameVersion": "current",
  "updatedAt": "2026-07-14",
  "reviewStatus": "draft",
  "reviewedBy": [],
  "summary": "铁镍矿的资源身份与获取证据。",
  "tags": [
    "acquisition",
    "resource",
    "official-generated"
  ]
}
