{
  "id": "currency.agnovidisc",
  "canonical": "Agnovidisc",
  "displayName": "名盘",
  "kind": "exchange-token",
  "aliases": [],
  "languageKey": "/Lotus/Language/TauPrequel/TauPrequelFinal/TwelveResourceCommonItemName",
  "officialSource": "DE Languages.bin /Lotus/Language/TauPrequel/TauPrequelFinal/TwelveResourceCommonItemName",
  "acquisitionDependency": {
    "acquisitionSummary": "在佩里塔叛乱中击败自由派敌人获得",
    "source": "Official Wiki Resources table: The Perita Rebellion enemy drops",
    "reviewStatus": "approved"
  },
  "category": "exchange-token",
  "reviewStatus": "approved",
  "boosterEffects": {
    "resourceAmount": "unknown",
    "resourceDropChance": "unknown",
    "exchangeCost": "unaffected",
    "scope": "in-mission-pickups-only",
    "evidence": []
  }
}
