{
  "id": "arcane-source.7c35ec06474f",
  "canonical": "Veil/Erato (Caches), Rotation B",
  "displayName": "面纱比邻星域/深情之域（奥影），轮次 B",
  "kind": "mission-reward",
  "aliases": [],
  "relation": {
    "locationId": "mission.erato-crewbattlenode541",
    "missionTypeId": "mission-type.orphix"
  },
  "mission": {
    "officialNodeId": "CrewBattleNode541",
    "planetCanonical": "Veil Proxima",
    "nodeCanonical": "Erato",
    "missionTypeCanonical": "ORPHIX",
    "missionTypeDisplayName": "奥影",
    "rotation": "B"
  },
  "localization": {
    "status": "official-zh",
    "rule": "禁止运行时猜译"
  },
  "source": "DE ExportRegions + Languages.bin; route from warframe-items"
}
