[
  {
    "id": "knowledge.acquisition.mod.turbo-protect-782aba7b",
    "kind": "knowledge",
    "module": "acquisition",
    "title": "极速防护",
    "subject": {
      "canonical": "Turbo Protect",
      "displayName": "极速防护",
      "category": "mod",
      "categoryRefs": [
        "parazonmod",
        "standardmod"
      ]
    },
    "officialUniqueName": "/Lotus/Upgrades/Mods/DataSpike/Potency/GainAntivirusAndSpeedOnUseMod",
    "maxRank": 3,
    "effectDetails": [
      "获得 10% 查杀进度和 25% 几率掉落杀毒 Mod"
    ],
    "rarity": "Rare",
    "polarity": "universal",
    "tradable": false,
    "prerequisites": [],
    "methodRefs": [],
    "acquisitionStatus": "stub",
    "sources": [
      {
        "url": "https://wiki.warframe.com/w/Turbo_Protect",
        "label": "Warframe Wiki - Turbo Protect"
      }
    ],
    "gameVersion": "warframe-items@1.1269.87",
    "updatedAt": "2026-07-13",
    "reviewStatus": "draft",
    "reviewedBy": [],
    "tags": [
      "acquisition",
      "mod",
      "standard-mod",
      "parazon-mod"
    ],
    "generator": {
      "name": "sync-mods",
      "version": 1
    }
  }
]
