[
  {
    "id": "knowledge.acquisition.mod.amalgam-argonak-metal-auger-29b98462",
    "kind": "knowledge",
    "module": "acquisition",
    "title": "并合 氩格纳克 合金钻头",
    "subject": {
      "canonical": "Amalgam Argonak Metal Auger",
      "displayName": "并合 氩格纳克 合金钻头",
      "category": "mod",
      "categoryRefs": [
        "primarymod",
        "standardmod"
      ]
    },
    "officialUniqueName": "/Lotus/Upgrades/Mods/DualSource/Rifle/ArgonakDaggerMod",
    "maxRank": 5,
    "effectDetails": [
      "+3 穿透",
      "匕首造成的伤害将减少 6 护甲。 敌人可通过穿透效果来显示。"
    ],
    "rarity": "Rare",
    "polarity": "naramon",
    "tradable": true,
    "prerequisites": [],
    "tips": [],
    "tipKeywords": [
      "本质机制",
      "具体计算公式",
      "加成层级",
      "与同类效果的叠加方式",
      "适用限制"
    ],
    "methodRefs": [],
    "acquisitionStatus": "stub",
    "sources": [
      {
        "url": "https://wiki.warframe.com/w/Amalgam_Argonak_Metal_Auger",
        "label": "Warframe Wiki - Amalgam Argonak Metal Auger"
      }
    ],
    "gameVersion": "warframe-items@1.1269.87",
    "updatedAt": "2026-07-15",
    "reviewStatus": "draft",
    "reviewedBy": [],
    "tags": [
      "acquisition",
      "mod",
      "standard-mod",
      "primary-mod"
    ],
    "generator": {
      "name": "sync-mods",
      "version": 4
    },
    "modAcquisition": {
      "generated": {
        "identity": {
          "officialUniqueName": "/Lotus/Upgrades/Mods/DualSource/Rifle/ArgonakDaggerMod",
          "canonical": "Amalgam Argonak Metal Auger",
          "displayName": "并合 氩格纳克 合金钻头",
          "maxRank": 5,
          "variant": "standard",
          "typeFolder": "primary"
        },
        "wiki": {
          "wiki": null,
          "methods": [],
          "evidence": [],
          "mechanicsEvidence": {
            "status": "draft",
            "notes": [],
            "usage": []
          },
          "unresolvedEntities": [
            {
              "kind": "wiki-page",
              "canonical": "Amalgam Argonak Metal Auger"
            }
          ],
          "status": "unresolved"
        },
        "officialDrops": [
          {
            "type": "official-drop",
            "sourceCanonical": "Jupiter/The Ropalolyst (Assassination)",
            "chance": 20,
            "quantity": 1,
            "rarity": "Uncommon",
            "reviewStatus": "draft",
            "provenance": {
              "source": "warframe-items",
              "input": "Mods.json",
              "officialUniqueName": "/Lotus/Upgrades/Mods/DualSource/Rifle/ArgonakDaggerMod"
            }
          }
        ]
      },
      "manual": {
        "methods": [],
        "methodRefs": [],
        "overrides": {},
        "reviewStatus": "draft",
        "reviewedBy": []
      }
    }
  }
]
