[
  {
    "id": "knowledge.acquisition.mod.mending-shot-e0c0dbec",
    "kind": "knowledge",
    "module": "acquisition",
    "title": "补愈射击",
    "subject": {
      "canonical": "Mending Shot",
      "displayName": "补愈射击",
      "category": "mod",
      "categoryRefs": [
        "primarymod",
        "standardmod"
      ]
    },
    "officialUniqueName": "/Lotus/Upgrades/Mods/Rifle/Event/Arbitration/ShootPickUpRifleMod",
    "maxRank": 10,
    "effectDetails": [
      "通过射击生命球来捡取它们，并获得 +110% 的额外效果。"
    ],
    "rarity": "Rare",
    "polarity": "madurai",
    "tradable": true,
    "prerequisites": [],
    "methodRefs": [],
    "acquisitionStatus": "stub",
    "sources": [
      {
        "url": "https://wiki.warframe.com/w/Mending_Shot",
        "label": "Warframe Wiki - Mending Shot"
      }
    ],
    "gameVersion": "warframe-items@1.1269.87",
    "updatedAt": "2026-07-13",
    "reviewStatus": "draft",
    "reviewedBy": [],
    "tags": [
      "acquisition",
      "mod",
      "standard-mod",
      "primary-mod"
    ],
    "generator": {
      "name": "sync-mods",
      "version": 1
    }
  }
]
