[
  {
    "id": "knowledge.acquisition.mod.smite-grineer-837914dc",
    "kind": "knowledge",
    "module": "acquisition",
    "title": "毁灭 克隆尼",
    "subject": {
      "canonical": "Smite Grineer",
      "displayName": "毁灭 克隆尼",
      "category": "mod",
      "categoryRefs": [
        "meleemod",
        "standardmod"
      ]
    },
    "officialUniqueName": "/Lotus/Upgrades/Mods/Melee/WeaponMeleeFactionDamageGrineer",
    "maxRank": 5,
    "effectDetails": [
      "x1.3 对 克隆尼 的伤害"
    ],
    "rarity": "Uncommon",
    "polarity": "madurai",
    "tradable": true,
    "prerequisites": [],
    "tips": [],
    "tipKeywords": [
      "本质机制",
      "具体计算公式",
      "加成层级",
      "与同类效果的叠加方式",
      "适用限制"
    ],
    "methodRefs": [],
    "acquisitionStatus": "complete",
    "sources": [
      {
        "url": "https://wiki.warframe.com/w/Smite_Grineer",
        "label": "Warframe Wiki - Smite Grineer"
      }
    ],
    "gameVersion": "warframe-items@1.1269.87",
    "updatedAt": "2026-07-22",
    "reviewStatus": "draft",
    "reviewedBy": [],
    "tags": [
      "acquisition",
      "mod",
      "standard-mod",
      "melee-mod"
    ],
    "generator": {
      "name": "sync-mods",
      "version": 4
    },
    "modAcquisition": {
      "generated": {
        "identity": {
          "officialUniqueName": "/Lotus/Upgrades/Mods/Melee/WeaponMeleeFactionDamageGrineer",
          "canonical": "Smite Grineer",
          "displayName": "毁灭 克隆尼",
          "maxRank": 5,
          "variant": "standard",
          "typeFolder": "melee"
        },
        "wiki": {
          "wiki": {
            "pageTitle": "Smite Grineer",
            "pageId": 112417,
            "revisionId": 2687253,
            "pageTimestamp": "2025-06-27T19:29:35Z",
            "compiledAt": "2026-07-17T01:48:34.614Z",
            "sourceDatabase": {
              "sha256": "861480127CC518FC3CCA9B28334AEEC16AB8AEA383D08EA5D3B55B701DA475B9",
              "size": 2322874368
            }
          },
          "methods": [
            {
              "type": "circuit-reward",
              "rotation": "A",
              "chance": 0.0067,
              "quantity": 1,
              "nodes": [],
              "availability": "unknown",
              "reviewStatus": "draft",
              "provenance": {
                "source": "local-wiki-sqlite",
                "pageTitle": "Smite Grineer",
                "pageId": 112417,
                "revisionId": 2687253,
                "section": "Mission Drop Tables",
                "excerpt": "The Circuit | Tier 1 The Circuit (Normal) | A | 0.67% | 1 | 0.0067 Accessed through Duviri 's The Circuit gamemode | | Accessed through Duviri 's The Circuit gamemode"
              },
              "missionTypeCanonical": "The Circuit",
              "missionTypeEntityId": "mission-type.the-circuit",
              "missionTypeDisplayName": "无尽回廊",
              "sourceCanonical": "Tier 1 The Circuit (Normal)"
            },
            {
              "type": "circuit-reward",
              "rotation": "A",
              "chance": 0.0067,
              "quantity": 1,
              "nodes": [],
              "availability": "unknown",
              "reviewStatus": "draft",
              "provenance": {
                "source": "local-wiki-sqlite",
                "pageTitle": "Smite Grineer",
                "pageId": 112417,
                "revisionId": 2687253,
                "section": "Mission Drop Tables",
                "excerpt": "The Circuit | Tier 3 The Circuit (Normal) | A | 0.67% | 1 | 0.0067 Accessed through Duviri 's The Circuit gamemode | | Accessed through Duviri 's The Circuit gamemode"
              },
              "missionTypeCanonical": "The Circuit",
              "missionTypeEntityId": "mission-type.the-circuit",
              "missionTypeDisplayName": "无尽回廊",
              "sourceCanonical": "Tier 3 The Circuit (Normal)"
            },
            {
              "type": "enemy-drop",
              "dropTableChance": 0.03,
              "itemChance": 0.0369,
              "chance": 0.0011070000000000001,
              "quantity": 1,
              "availability": "unknown",
              "reviewStatus": "draft",
              "provenance": {
                "source": "local-wiki-sqlite",
                "pageTitle": "Smite Grineer",
                "pageId": 112417,
                "revisionId": 2687253,
                "section": "Enemy Drop Tables",
                "excerpt": "Aurax Baculus | 3% | 3.69% | 0.1107% | 903 | 1 | 0.001107"
              },
              "sourceCanonical": "Aurax Baculus",
              "sourceEntityId": "enemy.aurax-baculus",
              "sourceDisplayName": "傲金杖兵"
            },
            {
              "type": "enemy-drop",
              "dropTableChance": 0.03,
              "itemChance": 0.1106,
              "chance": 0.0033179999999999998,
              "quantity": 1,
              "availability": "unknown",
              "reviewStatus": "draft",
              "provenance": {
                "source": "local-wiki-sqlite",
                "pageTitle": "Smite Grineer",
                "pageId": 112417,
                "revisionId": 2687253,
                "section": "Enemy Drop Tables",
                "excerpt": "Axio MOA | 3% | 11.06% | 0.3318% | 301 | 1 | 0.003318"
              },
              "sourceCanonical": "Axio MOA",
              "sourceEntityId": "enemy.axio-moa",
              "sourceDisplayName": "艾汐恐鸟"
            },
            {
              "type": "enemy-drop",
              "dropTableChance": 0.03,
              "itemChance": 0.0553,
              "chance": 0.0016589999999999999,
              "quantity": 1,
              "availability": "unknown",
              "reviewStatus": "draft",
              "provenance": {
                "source": "local-wiki-sqlite",
                "pageTitle": "Smite Grineer",
                "pageId": 112417,
                "revisionId": 2687253,
                "section": "Enemy Drop Tables",
                "excerpt": "Butcher | 3% | 5.53% | 0.1659% | 603 | 1 | 0.001659"
              },
              "sourceCanonical": "Butcher",
              "sourceEntityId": "enemy.butcher",
              "sourceDisplayName": "屠夫"
            },
            {
              "type": "enemy-drop",
              "dropTableChance": 0.15,
              "itemChance": 0.25,
              "chance": 0.0375,
              "quantity": 1,
              "availability": "unknown",
              "reviewStatus": "draft",
              "provenance": {
                "source": "local-wiki-sqlite",
                "pageTitle": "Smite Grineer",
                "pageId": 112417,
                "revisionId": 2687253,
                "section": "Enemy Drop Tables",
                "excerpt": "Demolisher Bailiff | 15% | 25% | 3.75% | 27 | 1 | 0.0375"
              },
              "sourceCanonical": "Demolisher Bailiff",
              "sourceEntityId": "enemy.demolisher-bailiff",
              "sourceDisplayName": "爆破型执法员"
            },
            {
              "type": "enemy-drop",
              "dropTableChance": 0.15,
              "itemChance": 0.25,
              "chance": 0.0375,
              "quantity": 1,
              "availability": "unknown",
              "reviewStatus": "draft",
              "provenance": {
                "source": "local-wiki-sqlite",
                "pageTitle": "Smite Grineer",
                "pageId": 112417,
                "revisionId": 2687253,
                "section": "Enemy Drop Tables",
                "excerpt": "Demolisher Devourer | 15% | 25% | 3.75% | 27 | 1 | 0.0375"
              },
              "sourceCanonical": "Demolisher Devourer",
              "sourceEntityId": "enemy.demolisher-devourer",
              "sourceDisplayName": "爆破型吞噬者"
            },
            {
              "type": "enemy-drop",
              "dropTableChance": 0.15,
              "itemChance": 0.25,
              "chance": 0.0375,
              "quantity": 1,
              "availability": "unknown",
              "reviewStatus": "draft",
              "provenance": {
                "source": "local-wiki-sqlite",
                "pageTitle": "Smite Grineer",
                "pageId": 112417,
                "revisionId": 2687253,
                "section": "Enemy Drop Tables",
                "excerpt": "Demolisher Expired | 15% | 25% | 3.75% | 27 | 1 | 0.0375"
              },
              "sourceCanonical": "Demolisher Expired",
              "sourceEntityId": "enemy.demolisher-expired",
              "sourceDisplayName": "爆破型除役者"
            },
            {
              "type": "enemy-drop",
              "dropTableChance": 0.15,
              "itemChance": 0.25,
              "chance": 0.0375,
              "quantity": 1,
              "availability": "unknown",
              "reviewStatus": "draft",
              "provenance": {
                "source": "local-wiki-sqlite",
                "pageTitle": "Smite Grineer",
                "pageId": 112417,
                "revisionId": 2687253,
                "section": "Enemy Drop Tables",
                "excerpt": "Demolisher Heavy Gunner | 15% | 25% | 3.75% | 27 | 1 | 0.0375"
              },
              "sourceCanonical": "Demolisher Heavy Gunner",
              "sourceEntityId": "enemy.demolisher-heavy-gunner",
              "sourceDisplayName": "爆破型重型机枪手"
            },
            {
              "type": "enemy-drop",
              "dropTableChance": 0.15,
              "itemChance": 0.25,
              "chance": 0.0375,
              "quantity": 1,
              "availability": "unknown",
              "reviewStatus": "draft",
              "provenance": {
                "source": "local-wiki-sqlite",
                "pageTitle": "Smite Grineer",
                "pageId": 112417,
                "revisionId": 2687253,
                "section": "Enemy Drop Tables",
                "excerpt": "Demolisher Kuva Guardian | 15% | 25% | 3.75% | 27 | 1 | 0.0375"
              },
              "sourceCanonical": "Demolisher Kuva Guardian",
              "sourceEntityId": "enemy.demolisher-kuva-guardian",
              "sourceDisplayName": "爆破型赤毒守卫者"
            },
            {
              "type": "enemy-drop",
              "dropTableChance": 0.15,
              "itemChance": 0.25,
              "chance": 0.0375,
              "quantity": 1,
              "availability": "unknown",
              "reviewStatus": "draft",
              "provenance": {
                "source": "local-wiki-sqlite",
                "pageTitle": "Smite Grineer",
                "pageId": 112417,
                "revisionId": 2687253,
                "section": "Enemy Drop Tables",
                "excerpt": "Demolisher Nox | 15% | 25% | 3.75% | 27 | 1 | 0.0375"
              },
              "sourceCanonical": "Demolisher Nox",
              "sourceEntityId": "enemy.demolisher-nox",
              "sourceDisplayName": "爆破型毒化者"
            },
            {
              "type": "enemy-drop",
              "dropTableChance": 0.03,
              "itemChance": 0.1106,
              "chance": 0.0033179999999999998,
              "quantity": 1,
              "availability": "unknown",
              "reviewStatus": "draft",
              "provenance": {
                "source": "local-wiki-sqlite",
                "pageTitle": "Smite Grineer",
                "pageId": 112417,
                "revisionId": 2687253,
                "section": "Enemy Drop Tables",
                "excerpt": "Denial Bursa | 3% | 11.06% | 0.3318% | 301 | 1 | 0.003318"
              },
              "sourceCanonical": "Denial Bursa",
              "sourceEntityId": "enemy.denial-bursa",
              "sourceDisplayName": "守护金流恐鸟"
            },
            {
              "type": "enemy-drop",
              "dropTableChance": 0.03,
              "itemChance": 0.0553,
              "chance": 0.0016589999999999999,
              "quantity": 1,
              "availability": "unknown",
              "reviewStatus": "draft",
              "provenance": {
                "source": "local-wiki-sqlite",
                "pageTitle": "Smite Grineer",
                "pageId": 112417,
                "revisionId": 2687253,
                "section": "Enemy Drop Tables",
                "excerpt": "Drahk Master | 3% | 5.53% | 0.1659% | 603 | 1 | 0.001659"
              },
              "sourceCanonical": "Drahk Master",
              "sourceEntityId": "enemy.drahk-master",
              "sourceDisplayName": "爪喀驯兽师"
            },
            {
              "type": "enemy-drop",
              "dropTableChance": 0.03,
              "itemChance": 0.1106,
              "chance": 0.0033179999999999998,
              "quantity": 1,
              "availability": "unknown",
              "reviewStatus": "draft",
              "provenance": {
                "source": "local-wiki-sqlite",
                "pageTitle": "Smite Grineer",
                "pageId": 112417,
                "revisionId": 2687253,
                "section": "Enemy Drop Tables",
                "excerpt": "Drekar Butcher | 3% | 11.06% | 0.3318% | 301 | 1 | 0.003318"
              },
              "sourceCanonical": "Drekar Butcher",
              "sourceEntityId": "enemy.drekar-butcher",
              "sourceDisplayName": "龙舰屠夫"
            },
            {
              "type": "enemy-drop",
              "dropTableChance": 0.03,
              "itemChance": 0.1106,
              "chance": 0.0033179999999999998,
              "quantity": 1,
              "availability": "unknown",
              "reviewStatus": "draft",
              "provenance": {
                "source": "local-wiki-sqlite",
                "pageTitle": "Smite Grineer",
                "pageId": 112417,
                "revisionId": 2687253,
                "section": "Enemy Drop Tables",
                "excerpt": "Drover Bursa | 3% | 11.06% | 0.3318% | 301 | 1 | 0.003318"
              },
              "sourceCanonical": "Drover Bursa",
              "sourceEntityId": "enemy.drover-bursa",
              "sourceDisplayName": "驱引金流恐鸟"
            },
            {
              "type": "enemy-drop",
              "dropTableChance": 0.03,
              "itemChance": 0.0553,
              "chance": 0.0016589999999999999,
              "quantity": 1,
              "availability": "unknown",
              "reviewStatus": "draft",
              "provenance": {
                "source": "local-wiki-sqlite",
                "pageTitle": "Smite Grineer",
                "pageId": 112417,
                "revisionId": 2687253,
                "section": "Enemy Drop Tables",
                "excerpt": "Frontier Bailiff | 3% | 5.53% | 0.1659% | 603 | 1 | 0.001659"
              },
              "sourceCanonical": "Frontier Bailiff",
              "sourceEntityId": "enemy.frontier-bailiff",
              "sourceDisplayName": "前线执法员"
            },
            {
              "type": "enemy-drop",
              "dropTableChance": 0.1,
              "itemChance": 0.0369,
              "chance": 0.00369,
              "quantity": 1,
              "availability": "unknown",
              "reviewStatus": "draft",
              "provenance": {
                "source": "local-wiki-sqlite",
                "pageTitle": "Smite Grineer",
                "pageId": 112417,
                "revisionId": 2687253,
                "section": "Enemy Drop Tables",
                "excerpt": "Ghoul Devourer | 10% | 3.69% | 0.369% | 271 | 1 | 0.00369"
              },
              "sourceCanonical": "Ghoul Devourer",
              "sourceEntityId": "enemy.ghoul-devourer",
              "sourceDisplayName": "吞噬者尸鬼"
            },
            {
              "type": "enemy-drop",
              "dropTableChance": 0.1,
              "itemChance": 0.0553,
              "chance": 0.00553,
              "quantity": 1,
              "availability": "unknown",
              "reviewStatus": "draft",
              "provenance": {
                "source": "local-wiki-sqlite",
                "pageTitle": "Smite Grineer",
                "pageId": 112417,
                "revisionId": 2687253,
                "section": "Enemy Drop Tables",
                "excerpt": "Ghoul Rictus | 10% | 5.53% | 0.553% | 181 | 1 | 0.00553"
              },
              "sourceCanonical": "Ghoul Rictus",
              "sourceEntityId": "enemy.ghoul-rictus",
              "sourceDisplayName": "裂嘴尸鬼"
            },
            {
              "type": "enemy-drop",
              "dropTableChance": 0.03,
              "itemChance": 0.0369,
              "chance": 0.0011070000000000001,
              "quantity": 1,
              "availability": "unknown",
              "reviewStatus": "draft",
              "provenance": {
                "source": "local-wiki-sqlite",
                "pageTitle": "Smite Grineer",
                "pageId": 112417,
                "revisionId": 2687253,
                "section": "Enemy Drop Tables",
                "excerpt": "Guardsman | 3% | 3.69% | 0.1107% | 903 | 1 | 0.001107"
              },
              "sourceCanonical": "Guardsman",
              "sourceEntityId": "enemy.guardsman",
              "sourceDisplayName": "禁卫军"
            },
            {
              "type": "enemy-drop",
              "dropTableChance": 0.03,
              "itemChance": 0.1106,
              "chance": 0.0033179999999999998,
              "quantity": 1,
              "availability": "unknown",
              "reviewStatus": "draft",
              "provenance": {
                "source": "local-wiki-sqlite",
                "pageTitle": "Smite Grineer",
                "pageId": 112417,
                "revisionId": 2687253,
                "section": "Enemy Drop Tables",
                "excerpt": "Isolator Bursa | 3% | 11.06% | 0.3318% | 301 | 1 | 0.003318"
              },
              "sourceCanonical": "Isolator Bursa",
              "sourceEntityId": "enemy.isolator-bursa",
              "sourceDisplayName": "隔离金流恐鸟"
            },
            {
              "type": "enemy-drop",
              "dropTableChance": 0.03,
              "itemChance": 0.1106,
              "chance": 0.0033179999999999998,
              "quantity": 1,
              "availability": "unknown",
              "reviewStatus": "draft",
              "provenance": {
                "source": "local-wiki-sqlite",
                "pageTitle": "Smite Grineer",
                "pageId": 112417,
                "revisionId": 2687253,
                "section": "Enemy Drop Tables",
                "excerpt": "Juno Dera MOA | 3% | 11.06% | 0.3318% | 301 | 1 | 0.003318"
              },
              "sourceCanonical": "Juno Dera MOA",
              "sourceEntityId": "enemy.juno-dera-moa",
              "sourceDisplayName": "朱诺德拉恐鸟"
            },
            {
              "type": "enemy-drop",
              "dropTableChance": 0.03,
              "itemChance": 0.1106,
              "chance": 0.0033179999999999998,
              "quantity": 1,
              "availability": "unknown",
              "reviewStatus": "draft",
              "provenance": {
                "source": "local-wiki-sqlite",
                "pageTitle": "Smite Grineer",
                "pageId": 112417,
                "revisionId": 2687253,
                "section": "Enemy Drop Tables",
                "excerpt": "Juno Disc MOA | 3% | 11.06% | 0.3318% | 301 | 1 | 0.003318"
              },
              "sourceCanonical": "Juno Disc MOA",
              "sourceEntityId": "enemy.juno-disc-moa",
              "sourceDisplayName": "朱诺圆盘恐鸟"
            },
            {
              "type": "enemy-drop",
              "dropTableChance": 0.03,
              "itemChance": 0.0737,
              "chance": 0.002211,
              "quantity": 1,
              "availability": "unknown",
              "reviewStatus": "draft",
              "provenance": {
                "source": "local-wiki-sqlite",
                "pageTitle": "Smite Grineer",
                "pageId": 112417,
                "revisionId": 2687253,
                "section": "Enemy Drop Tables",
                "excerpt": "Juno Geminex MOA | 3% | 7.37% | 0.2211% | 452 | 1 | 0.002211"
              },
              "sourceCanonical": "Juno Geminex MOA",
              "sourceEntityId": "enemy.juno-geminex-moa",
              "sourceDisplayName": "朱诺双子炮恐鸟"
            },
            {
              "type": "enemy-drop",
              "dropTableChance": 0.03,
              "itemChance": 0.1106,
              "chance": 0.0033179999999999998,
              "quantity": 1,
              "availability": "unknown",
              "reviewStatus": "draft",
              "provenance": {
                "source": "local-wiki-sqlite",
                "pageTitle": "Smite Grineer",
                "pageId": 112417,
                "revisionId": 2687253,
                "section": "Enemy Drop Tables",
                "excerpt": "Juno Glaxion MOA | 3% | 11.06% | 0.3318% | 301 | 1 | 0.003318"
              },
              "sourceCanonical": "Juno Glaxion MOA",
              "sourceEntityId": "enemy.juno-glaxion-moa",
              "sourceDisplayName": "朱诺冷冻光束步枪恐鸟"
            },
            {
              "type": "enemy-drop",
              "dropTableChance": 0.03,
              "itemChance": 0.0553,
              "chance": 0.0016589999999999999,
              "quantity": 1,
              "availability": "unknown",
              "reviewStatus": "draft",
              "provenance": {
                "source": "local-wiki-sqlite",
                "pageTitle": "Smite Grineer",
                "pageId": 112417,
                "revisionId": 2687253,
                "section": "Enemy Drop Tables",
                "excerpt": "Kuva Butcher | 3% | 5.53% | 0.1659% | 603 | 1 | 0.001659"
              },
              "sourceCanonical": "Kuva Butcher",
              "sourceEntityId": "enemy.kuva-butcher",
              "sourceDisplayName": "赤毒屠夫"
            },
            {
              "type": "enemy-drop",
              "dropTableChance": 0.03,
              "itemChance": 0.0553,
              "chance": 0.0016589999999999999,
              "quantity": 1,
              "availability": "unknown",
              "reviewStatus": "draft",
              "provenance": {
                "source": "local-wiki-sqlite",
                "pageTitle": "Smite Grineer",
                "pageId": 112417,
                "revisionId": 2687253,
                "section": "Enemy Drop Tables",
                "excerpt": "Kuva Drahk Master | 3% | 5.53% | 0.1659% | 603 | 1 | 0.001659"
              },
              "sourceCanonical": "Kuva Drahk Master",
              "sourceEntityId": "enemy.kuva-drahk-master",
              "sourceDisplayName": "赤毒爪喀驯兽师"
            },
            {
              "type": "enemy-drop",
              "dropTableChance": 0.03,
              "itemChance": 0.1106,
              "chance": 0.0033179999999999998,
              "quantity": 1,
              "availability": "unknown",
              "reviewStatus": "draft",
              "provenance": {
                "source": "local-wiki-sqlite",
                "pageTitle": "Smite Grineer",
                "pageId": 112417,
                "revisionId": 2687253,
                "section": "Enemy Drop Tables",
                "excerpt": "MOA | 3% | 11.06% | 0.3318% | 301 | 1 | 0.003318"
              },
              "sourceCanonical": "MOA",
              "sourceEntityId": "enemy.moa",
              "sourceDisplayName": "恐鸟"
            },
            {
              "type": "enemy-drop",
              "dropTableChance": 0.3,
              "itemChance": 0.2143,
              "chance": 0.06429,
              "quantity": 1,
              "availability": "unknown",
              "reviewStatus": "draft",
              "provenance": {
                "source": "local-wiki-sqlite",
                "pageTitle": "Smite Grineer",
                "pageId": 112417,
                "revisionId": 2687253,
                "section": "Enemy Drop Tables",
                "excerpt": "Mimic | 30% | 21.43% | 6.429% | 16 | 1 | 0.06429"
              },
              "sourceCanonical": "Mimic",
              "sourceEntityId": "enemy.mimic",
              "sourceDisplayName": "拟态者"
            },
            {
              "type": "enemy-drop",
              "dropTableChance": 0.03,
              "itemChance": 0.1106,
              "chance": 0.0033179999999999998,
              "quantity": 1,
              "availability": "unknown",
              "reviewStatus": "draft",
              "provenance": {
                "source": "local-wiki-sqlite",
                "pageTitle": "Smite Grineer",
                "pageId": 112417,
                "revisionId": 2687253,
                "section": "Enemy Drop Tables",
                "excerpt": "Minima MOA | 3% | 11.06% | 0.3318% | 301 | 1 | 0.003318"
              },
              "sourceCanonical": "Minima MOA",
              "sourceEntityId": "enemy.minima-moa",
              "sourceDisplayName": "微型恐鸟"
            },
            {
              "type": "enemy-drop",
              "dropTableChance": 0.03,
              "itemChance": 0.1106,
              "chance": 0.0033179999999999998,
              "quantity": 1,
              "availability": "unknown",
              "reviewStatus": "draft",
              "provenance": {
                "source": "local-wiki-sqlite",
                "pageTitle": "Smite Grineer",
                "pageId": 112417,
                "revisionId": 2687253,
                "section": "Enemy Drop Tables",
                "excerpt": "Narmer Dera MOA | 3% | 11.06% | 0.3318% | 301 | 1 | 0.003318"
              },
              "sourceCanonical": "Narmer Dera MOA",
              "sourceEntityId": "enemy.narmer-dera-moa",
              "sourceDisplayName": "合一众德拉恐鸟"
            },
            {
              "type": "enemy-drop",
              "dropTableChance": 0.03,
              "itemChance": 0.1106,
              "chance": 0.0033179999999999998,
              "quantity": 1,
              "availability": "unknown",
              "reviewStatus": "draft",
              "provenance": {
                "source": "local-wiki-sqlite",
                "pageTitle": "Smite Grineer",
                "pageId": 112417,
                "revisionId": 2687253,
                "section": "Enemy Drop Tables",
                "excerpt": "Narmer Disc MOA | 3% | 11.06% | 0.3318% | 301 | 1 | 0.003318"
              },
              "sourceCanonical": "Narmer Disc MOA",
              "sourceEntityId": "enemy.narmer-disc-moa",
              "sourceDisplayName": "合一众圆盘恐鸟"
            },
            {
              "type": "enemy-drop",
              "dropTableChance": 0.03,
              "itemChance": 0.0737,
              "chance": 0.002211,
              "quantity": 1,
              "availability": "unknown",
              "reviewStatus": "draft",
              "provenance": {
                "source": "local-wiki-sqlite",
                "pageTitle": "Smite Grineer",
                "pageId": 112417,
                "revisionId": 2687253,
                "section": "Enemy Drop Tables",
                "excerpt": "Narmer Geminex MOA | 3% | 7.37% | 0.2211% | 452 | 1 | 0.002211"
              },
              "sourceCanonical": "Narmer Geminex MOA",
              "sourceEntityId": "enemy.narmer-geminex-moa",
              "sourceDisplayName": "合一众双子炮恐鸟"
            },
            {
              "type": "enemy-drop",
              "dropTableChance": 0.03,
              "itemChance": 0.0737,
              "chance": 0.002211,
              "quantity": 1,
              "availability": "unknown",
              "reviewStatus": "draft",
              "provenance": {
                "source": "local-wiki-sqlite",
                "pageTitle": "Smite Grineer",
                "pageId": 112417,
                "revisionId": 2687253,
                "section": "Enemy Drop Tables",
                "excerpt": "Narmer Glaxion MOA | 3% | 7.37% | 0.2211% | 452 | 1 | 0.002211"
              },
              "sourceCanonical": "Narmer Glaxion MOA",
              "sourceEntityId": "enemy.narmer-glaxion-moa",
              "sourceDisplayName": "合一众冷冻光束步枪恐鸟"
            },
            {
              "type": "enemy-drop",
              "dropTableChance": 0.03,
              "itemChance": 0.1106,
              "chance": 0.0033179999999999998,
              "quantity": 1,
              "availability": "unknown",
              "reviewStatus": "draft",
              "provenance": {
                "source": "local-wiki-sqlite",
                "pageTitle": "Smite Grineer",
                "pageId": 112417,
                "revisionId": 2687253,
                "section": "Enemy Drop Tables",
                "excerpt": "Orm MOA | 3% | 11.06% | 0.3318% | 301 | 1 | 0.003318"
              },
              "sourceCanonical": "Orm MOA",
              "sourceEntityId": "enemy.orm-moa",
              "sourceDisplayName": "奥穆恐鸟"
            },
            {
              "type": "enemy-drop",
              "dropTableChance": 0.03,
              "itemChance": 0.1106,
              "chance": 0.0033179999999999998,
              "quantity": 1,
              "availability": "unknown",
              "reviewStatus": "draft",
              "provenance": {
                "source": "local-wiki-sqlite",
                "pageTitle": "Smite Grineer",
                "pageId": 112417,
                "revisionId": 2687253,
                "section": "Enemy Drop Tables",
                "excerpt": "Ratel | 3% | 11.06% | 0.3318% | 301 | 1 | 0.003318"
              },
              "sourceCanonical": "Ratel",
              "sourceEntityId": "enemy.ratel",
              "sourceDisplayName": "蜜獾"
            },
            {
              "type": "enemy-drop",
              "dropTableChance": 0.03,
              "itemChance": 0.1106,
              "chance": 0.0033179999999999998,
              "quantity": 1,
              "availability": "unknown",
              "reviewStatus": "draft",
              "provenance": {
                "source": "local-wiki-sqlite",
                "pageTitle": "Smite Grineer",
                "pageId": 112417,
                "revisionId": 2687253,
                "section": "Enemy Drop Tables",
                "excerpt": "Syzygy Denial Bursa | 3% | 11.06% | 0.3318% | 301 | 1 | 0.003318"
              },
              "sourceCanonical": "Syzygy Denial Bursa",
              "sourceEntityId": "enemy.syzygy-denial-bursa",
              "sourceDisplayName": "朔望守护金流恐鸟"
            },
            {
              "type": "enemy-drop",
              "dropTableChance": 0.03,
              "itemChance": 0.1106,
              "chance": 0.0033179999999999998,
              "quantity": 1,
              "availability": "unknown",
              "reviewStatus": "draft",
              "provenance": {
                "source": "local-wiki-sqlite",
                "pageTitle": "Smite Grineer",
                "pageId": 112417,
                "revisionId": 2687253,
                "section": "Enemy Drop Tables",
                "excerpt": "Tarask Bursa | 3% | 11.06% | 0.3318% | 301 | 1 | 0.003318"
              },
              "sourceCanonical": "Tarask Bursa",
              "sourceEntityId": "enemy.tarask-bursa",
              "sourceDisplayName": "穷凶金流恐鸟"
            },
            {
              "type": "enemy-drop",
              "dropTableChance": 0.03,
              "itemChance": 0.1106,
              "chance": 0.0033179999999999998,
              "quantity": 1,
              "availability": "unknown",
              "reviewStatus": "draft",
              "provenance": {
                "source": "local-wiki-sqlite",
                "pageTitle": "Smite Grineer",
                "pageId": 112417,
                "revisionId": 2687253,
                "section": "Enemy Drop Tables",
                "excerpt": "Taro MOA | 3% | 11.06% | 0.3318% | 301 | 1 | 0.003318"
              },
              "sourceCanonical": "Taro MOA",
              "sourceEntityId": "enemy.taro-moa",
              "sourceDisplayName": "泰洛恐鸟"
            },
            {
              "type": "enemy-drop",
              "dropTableChance": 0.03,
              "itemChance": 0.0553,
              "chance": 0.0016589999999999999,
              "quantity": 1,
              "availability": "unknown",
              "reviewStatus": "draft",
              "provenance": {
                "source": "local-wiki-sqlite",
                "pageTitle": "Smite Grineer",
                "pageId": 112417,
                "revisionId": 2687253,
                "section": "Enemy Drop Tables",
                "excerpt": "Tusk Butcher | 3% | 5.53% | 0.1659% | 603 | 1 | 0.001659"
              },
              "sourceCanonical": "Tusk Butcher",
              "sourceEntityId": "enemy.tusk-butcher",
              "sourceDisplayName": "巨牙屠夫"
            },
            {
              "type": "enemy-drop",
              "dropTableChance": 0.03,
              "itemChance": 0.1106,
              "chance": 0.0033179999999999998,
              "quantity": 1,
              "availability": "unknown",
              "reviewStatus": "draft",
              "provenance": {
                "source": "local-wiki-sqlite",
                "pageTitle": "Smite Grineer",
                "pageId": 112417,
                "revisionId": 2687253,
                "section": "Enemy Drop Tables",
                "excerpt": "Vapos MOA | 3% | 11.06% | 0.3318% | 301 | 1 | 0.003318"
              },
              "sourceCanonical": "Vapos MOA",
              "sourceEntityId": "enemy.vapos-moa",
              "sourceDisplayName": "气雾恐鸟"
            },
            {
              "type": "enemy-drop",
              "dropTableChance": 0.03,
              "itemChance": 0.1106,
              "chance": 0.0033179999999999998,
              "quantity": 1,
              "availability": "unknown",
              "reviewStatus": "draft",
              "provenance": {
                "source": "local-wiki-sqlite",
                "pageTitle": "Smite Grineer",
                "pageId": 112417,
                "revisionId": 2687253,
                "section": "Enemy Drop Tables",
                "excerpt": "Vorac MOA | 3% | 11.06% | 0.3318% | 301 | 1 | 0.003318"
              },
              "sourceCanonical": "Vorac MOA",
              "sourceEntityId": "enemy.vorac-moa",
              "sourceDisplayName": "沃拉恐鸟"
            }
          ],
          "evidence": [],
          "mechanicsEvidence": {
            "status": "draft",
            "notes": [
              {
                "reviewStatus": "draft",
                "provenance": {
                  "source": "local-wiki-sqlite",
                  "pageTitle": "Smite Grineer",
                  "pageId": 112417,
                  "revisionId": 2687253,
                  "section": "Notes",
                  "excerpt": "Has no effect on Corrupted and Narmer Grineer (e.g. Corrupted Lancer , Narmer Lancer )."
                }
              },
              {
                "reviewStatus": "draft",
                "provenance": {
                  "source": "local-wiki-sqlite",
                  "pageTitle": "Smite Grineer",
                  "pageId": 112417,
                  "revisionId": 2687253,
                  "section": "Notes",
                  "excerpt": "Despite being listed as a multiplier, it will stack additively with other sources of Damage to Grineer."
                }
              },
              {
                "reviewStatus": "draft",
                "provenance": {
                  "source": "local-wiki-sqlite",
                  "pageTitle": "Smite Grineer",
                  "pageId": 112417,
                  "revisionId": 2687253,
                  "section": "Notes",
                  "excerpt": "For example, if you had a Riven Mod with x0.5 Damage to Grineer and a max rank Smite Grineer with x1.3 Damage to Grineer, you would have a 1 - 0.5 + 0.3 = x0.8 multiplier for damage against Grineer with both mods equipped."
                }
              }
            ],
            "usage": []
          },
          "unresolvedEntities": [],
          "status": "complete"
        },
        "officialDrops": [
          {
            "type": "official-drop",
            "sourceCanonical": "Aurax Baculus",
            "chance": 0.0011,
            "quantity": 1,
            "rarity": "Rare",
            "reviewStatus": "draft",
            "provenance": {
              "source": "warframe-items",
              "input": "Mods.json",
              "officialUniqueName": "/Lotus/Upgrades/Mods/Melee/WeaponMeleeFactionDamageGrineer",
              "itemCanonical": "Smite Grineer"
            }
          },
          {
            "type": "official-drop",
            "sourceCanonical": "Guardsman",
            "chance": 0.0011,
            "quantity": 1,
            "rarity": "Rare",
            "reviewStatus": "draft",
            "provenance": {
              "source": "warframe-items",
              "input": "Mods.json",
              "officialUniqueName": "/Lotus/Upgrades/Mods/Melee/WeaponMeleeFactionDamageGrineer",
              "itemCanonical": "Smite Grineer"
            }
          },
          {
            "type": "official-drop",
            "sourceCanonical": "Butcher",
            "chance": 0.0017,
            "quantity": 1,
            "rarity": "Rare",
            "reviewStatus": "draft",
            "provenance": {
              "source": "warframe-items",
              "input": "Mods.json",
              "officialUniqueName": "/Lotus/Upgrades/Mods/Melee/WeaponMeleeFactionDamageGrineer",
              "itemCanonical": "Smite Grineer"
            }
          },
          {
            "type": "official-drop",
            "sourceCanonical": "Drahk Master",
            "chance": 0.0017,
            "quantity": 1,
            "rarity": "Rare",
            "reviewStatus": "draft",
            "provenance": {
              "source": "warframe-items",
              "input": "Mods.json",
              "officialUniqueName": "/Lotus/Upgrades/Mods/Melee/WeaponMeleeFactionDamageGrineer",
              "itemCanonical": "Smite Grineer"
            }
          },
          {
            "type": "official-drop",
            "sourceCanonical": "Frontier Bailiff",
            "chance": 0.0017,
            "quantity": 1,
            "rarity": "Rare",
            "reviewStatus": "draft",
            "provenance": {
              "source": "warframe-items",
              "input": "Mods.json",
              "officialUniqueName": "/Lotus/Upgrades/Mods/Melee/WeaponMeleeFactionDamageGrineer",
              "itemCanonical": "Smite Grineer"
            }
          },
          {
            "type": "official-drop",
            "sourceCanonical": "Kuva Butcher",
            "chance": 0.0017,
            "quantity": 1,
            "rarity": "Rare",
            "reviewStatus": "draft",
            "provenance": {
              "source": "warframe-items",
              "input": "Mods.json",
              "officialUniqueName": "/Lotus/Upgrades/Mods/Melee/WeaponMeleeFactionDamageGrineer",
              "itemCanonical": "Smite Grineer"
            }
          },
          {
            "type": "official-drop",
            "sourceCanonical": "Kuva Drahk Master",
            "chance": 0.0017,
            "quantity": 1,
            "rarity": "Rare",
            "reviewStatus": "draft",
            "provenance": {
              "source": "warframe-items",
              "input": "Mods.json",
              "officialUniqueName": "/Lotus/Upgrades/Mods/Melee/WeaponMeleeFactionDamageGrineer",
              "itemCanonical": "Smite Grineer"
            }
          },
          {
            "type": "official-drop",
            "sourceCanonical": "Tusk Butcher",
            "chance": 0.0017,
            "quantity": 1,
            "rarity": "Rare",
            "reviewStatus": "draft",
            "provenance": {
              "source": "warframe-items",
              "input": "Mods.json",
              "officialUniqueName": "/Lotus/Upgrades/Mods/Melee/WeaponMeleeFactionDamageGrineer",
              "itemCanonical": "Smite Grineer"
            }
          },
          {
            "type": "official-drop",
            "sourceCanonical": "Juno Geminex Moa",
            "chance": 0.0022,
            "quantity": 1,
            "rarity": "Rare",
            "reviewStatus": "draft",
            "provenance": {
              "source": "warframe-items",
              "input": "Mods.json",
              "officialUniqueName": "/Lotus/Upgrades/Mods/Melee/WeaponMeleeFactionDamageGrineer",
              "itemCanonical": "Smite Grineer"
            }
          },
          {
            "type": "official-drop",
            "sourceCanonical": "Narmer Geminex Moa",
            "chance": 0.0022,
            "quantity": 1,
            "rarity": "Rare",
            "reviewStatus": "draft",
            "provenance": {
              "source": "warframe-items",
              "input": "Mods.json",
              "officialUniqueName": "/Lotus/Upgrades/Mods/Melee/WeaponMeleeFactionDamageGrineer",
              "itemCanonical": "Smite Grineer"
            }
          },
          {
            "type": "official-drop",
            "sourceCanonical": "Axio Moa",
            "chance": 0.0033,
            "quantity": 1,
            "rarity": "Uncommon",
            "reviewStatus": "draft",
            "provenance": {
              "source": "warframe-items",
              "input": "Mods.json",
              "officialUniqueName": "/Lotus/Upgrades/Mods/Melee/WeaponMeleeFactionDamageGrineer",
              "itemCanonical": "Smite Grineer"
            }
          },
          {
            "type": "official-drop",
            "sourceCanonical": "Denial Bursa",
            "chance": 0.0033,
            "quantity": 1,
            "rarity": "Uncommon",
            "reviewStatus": "draft",
            "provenance": {
              "source": "warframe-items",
              "input": "Mods.json",
              "officialUniqueName": "/Lotus/Upgrades/Mods/Melee/WeaponMeleeFactionDamageGrineer",
              "itemCanonical": "Smite Grineer"
            }
          },
          {
            "type": "official-drop",
            "sourceCanonical": "Drekar Butcher",
            "chance": 0.0033,
            "quantity": 1,
            "rarity": "Uncommon",
            "reviewStatus": "draft",
            "provenance": {
              "source": "warframe-items",
              "input": "Mods.json",
              "officialUniqueName": "/Lotus/Upgrades/Mods/Melee/WeaponMeleeFactionDamageGrineer",
              "itemCanonical": "Smite Grineer"
            }
          },
          {
            "type": "official-drop",
            "sourceCanonical": "Drover Bursa",
            "chance": 0.0033,
            "quantity": 1,
            "rarity": "Uncommon",
            "reviewStatus": "draft",
            "provenance": {
              "source": "warframe-items",
              "input": "Mods.json",
              "officialUniqueName": "/Lotus/Upgrades/Mods/Melee/WeaponMeleeFactionDamageGrineer",
              "itemCanonical": "Smite Grineer"
            }
          },
          {
            "type": "official-drop",
            "sourceCanonical": "Isolator Bursa",
            "chance": 0.0033,
            "quantity": 1,
            "rarity": "Uncommon",
            "reviewStatus": "draft",
            "provenance": {
              "source": "warframe-items",
              "input": "Mods.json",
              "officialUniqueName": "/Lotus/Upgrades/Mods/Melee/WeaponMeleeFactionDamageGrineer",
              "itemCanonical": "Smite Grineer"
            }
          },
          {
            "type": "official-drop",
            "sourceCanonical": "Juno Dera Moa",
            "chance": 0.0033,
            "quantity": 1,
            "rarity": "Uncommon",
            "reviewStatus": "draft",
            "provenance": {
              "source": "warframe-items",
              "input": "Mods.json",
              "officialUniqueName": "/Lotus/Upgrades/Mods/Melee/WeaponMeleeFactionDamageGrineer",
              "itemCanonical": "Smite Grineer"
            }
          },
          {
            "type": "official-drop",
            "sourceCanonical": "Juno Disc Moa",
            "chance": 0.0033,
            "quantity": 1,
            "rarity": "Uncommon",
            "reviewStatus": "draft",
            "provenance": {
              "source": "warframe-items",
              "input": "Mods.json",
              "officialUniqueName": "/Lotus/Upgrades/Mods/Melee/WeaponMeleeFactionDamageGrineer",
              "itemCanonical": "Smite Grineer"
            }
          },
          {
            "type": "official-drop",
            "sourceCanonical": "Juno Glaxion Moa",
            "chance": 0.0033,
            "quantity": 1,
            "rarity": "Uncommon",
            "reviewStatus": "draft",
            "provenance": {
              "source": "warframe-items",
              "input": "Mods.json",
              "officialUniqueName": "/Lotus/Upgrades/Mods/Melee/WeaponMeleeFactionDamageGrineer",
              "itemCanonical": "Smite Grineer"
            }
          },
          {
            "type": "official-drop",
            "sourceCanonical": "Minima Moa",
            "chance": 0.0033,
            "quantity": 1,
            "rarity": "Uncommon",
            "reviewStatus": "draft",
            "provenance": {
              "source": "warframe-items",
              "input": "Mods.json",
              "officialUniqueName": "/Lotus/Upgrades/Mods/Melee/WeaponMeleeFactionDamageGrineer",
              "itemCanonical": "Smite Grineer"
            }
          },
          {
            "type": "official-drop",
            "sourceCanonical": "Moa",
            "chance": 0.0033,
            "quantity": 1,
            "rarity": "Uncommon",
            "reviewStatus": "draft",
            "provenance": {
              "source": "warframe-items",
              "input": "Mods.json",
              "officialUniqueName": "/Lotus/Upgrades/Mods/Melee/WeaponMeleeFactionDamageGrineer",
              "itemCanonical": "Smite Grineer"
            }
          },
          {
            "type": "official-drop",
            "sourceCanonical": "Narmer Dera Moa",
            "chance": 0.0033,
            "quantity": 1,
            "rarity": "Uncommon",
            "reviewStatus": "draft",
            "provenance": {
              "source": "warframe-items",
              "input": "Mods.json",
              "officialUniqueName": "/Lotus/Upgrades/Mods/Melee/WeaponMeleeFactionDamageGrineer",
              "itemCanonical": "Smite Grineer"
            }
          },
          {
            "type": "official-drop",
            "sourceCanonical": "Narmer Disc Moa",
            "chance": 0.0033,
            "quantity": 1,
            "rarity": "Uncommon",
            "reviewStatus": "draft",
            "provenance": {
              "source": "warframe-items",
              "input": "Mods.json",
              "officialUniqueName": "/Lotus/Upgrades/Mods/Melee/WeaponMeleeFactionDamageGrineer",
              "itemCanonical": "Smite Grineer"
            }
          },
          {
            "type": "official-drop",
            "sourceCanonical": "Narmer Glaxion Moa",
            "chance": 0.0033,
            "quantity": 1,
            "rarity": "Uncommon",
            "reviewStatus": "draft",
            "provenance": {
              "source": "warframe-items",
              "input": "Mods.json",
              "officialUniqueName": "/Lotus/Upgrades/Mods/Melee/WeaponMeleeFactionDamageGrineer",
              "itemCanonical": "Smite Grineer"
            }
          },
          {
            "type": "official-drop",
            "sourceCanonical": "Orm Moa",
            "chance": 0.0033,
            "quantity": 1,
            "rarity": "Uncommon",
            "reviewStatus": "draft",
            "provenance": {
              "source": "warframe-items",
              "input": "Mods.json",
              "officialUniqueName": "/Lotus/Upgrades/Mods/Melee/WeaponMeleeFactionDamageGrineer",
              "itemCanonical": "Smite Grineer"
            }
          },
          {
            "type": "official-drop",
            "sourceCanonical": "Ratel",
            "chance": 0.0033,
            "quantity": 1,
            "rarity": "Uncommon",
            "reviewStatus": "draft",
            "provenance": {
              "source": "warframe-items",
              "input": "Mods.json",
              "officialUniqueName": "/Lotus/Upgrades/Mods/Melee/WeaponMeleeFactionDamageGrineer",
              "itemCanonical": "Smite Grineer"
            }
          },
          {
            "type": "official-drop",
            "sourceCanonical": "Tarask Bursa",
            "chance": 0.0033,
            "quantity": 1,
            "rarity": "Uncommon",
            "reviewStatus": "draft",
            "provenance": {
              "source": "warframe-items",
              "input": "Mods.json",
              "officialUniqueName": "/Lotus/Upgrades/Mods/Melee/WeaponMeleeFactionDamageGrineer",
              "itemCanonical": "Smite Grineer"
            }
          },
          {
            "type": "official-drop",
            "sourceCanonical": "Taro Moa",
            "chance": 0.0033,
            "quantity": 1,
            "rarity": "Uncommon",
            "reviewStatus": "draft",
            "provenance": {
              "source": "warframe-items",
              "input": "Mods.json",
              "officialUniqueName": "/Lotus/Upgrades/Mods/Melee/WeaponMeleeFactionDamageGrineer",
              "itemCanonical": "Smite Grineer"
            }
          },
          {
            "type": "official-drop",
            "sourceCanonical": "Vapos Moa",
            "chance": 0.0033,
            "quantity": 1,
            "rarity": "Uncommon",
            "reviewStatus": "draft",
            "provenance": {
              "source": "warframe-items",
              "input": "Mods.json",
              "officialUniqueName": "/Lotus/Upgrades/Mods/Melee/WeaponMeleeFactionDamageGrineer",
              "itemCanonical": "Smite Grineer"
            }
          },
          {
            "type": "official-drop",
            "sourceCanonical": "Vorac Moa",
            "chance": 0.0033,
            "quantity": 1,
            "rarity": "Uncommon",
            "reviewStatus": "draft",
            "provenance": {
              "source": "warframe-items",
              "input": "Mods.json",
              "officialUniqueName": "/Lotus/Upgrades/Mods/Melee/WeaponMeleeFactionDamageGrineer",
              "itemCanonical": "Smite Grineer"
            }
          },
          {
            "type": "official-drop",
            "sourceCanonical": "Ghoul Devourer",
            "chance": 0.0037,
            "quantity": 1,
            "rarity": "Rare",
            "reviewStatus": "draft",
            "provenance": {
              "source": "warframe-items",
              "input": "Mods.json",
              "officialUniqueName": "/Lotus/Upgrades/Mods/Melee/WeaponMeleeFactionDamageGrineer",
              "itemCanonical": "Smite Grineer"
            }
          },
          {
            "type": "official-drop",
            "sourceCanonical": "Ghoul Rictus",
            "chance": 0.0055,
            "quantity": 1,
            "rarity": "Rare",
            "reviewStatus": "draft",
            "provenance": {
              "source": "warframe-items",
              "input": "Mods.json",
              "officialUniqueName": "/Lotus/Upgrades/Mods/Melee/WeaponMeleeFactionDamageGrineer",
              "itemCanonical": "Smite Grineer"
            }
          },
          {
            "type": "official-drop",
            "sourceCanonical": "Demolisher Bailiff",
            "chance": 0.0375,
            "quantity": 1,
            "rarity": "Uncommon",
            "reviewStatus": "draft",
            "provenance": {
              "source": "warframe-items",
              "input": "Mods.json",
              "officialUniqueName": "/Lotus/Upgrades/Mods/Melee/WeaponMeleeFactionDamageGrineer",
              "itemCanonical": "Smite Grineer"
            }
          },
          {
            "type": "official-drop",
            "sourceCanonical": "Demolisher Devourer",
            "chance": 0.0375,
            "quantity": 1,
            "rarity": "Uncommon",
            "reviewStatus": "draft",
            "provenance": {
              "source": "warframe-items",
              "input": "Mods.json",
              "officialUniqueName": "/Lotus/Upgrades/Mods/Melee/WeaponMeleeFactionDamageGrineer",
              "itemCanonical": "Smite Grineer"
            }
          },
          {
            "type": "official-drop",
            "sourceCanonical": "Demolisher Expired",
            "chance": 0.0375,
            "quantity": 1,
            "rarity": "Uncommon",
            "reviewStatus": "draft",
            "provenance": {
              "source": "warframe-items",
              "input": "Mods.json",
              "officialUniqueName": "/Lotus/Upgrades/Mods/Melee/WeaponMeleeFactionDamageGrineer",
              "itemCanonical": "Smite Grineer"
            }
          },
          {
            "type": "official-drop",
            "sourceCanonical": "Demolisher Heavy Gunner",
            "chance": 0.0375,
            "quantity": 1,
            "rarity": "Uncommon",
            "reviewStatus": "draft",
            "provenance": {
              "source": "warframe-items",
              "input": "Mods.json",
              "officialUniqueName": "/Lotus/Upgrades/Mods/Melee/WeaponMeleeFactionDamageGrineer",
              "itemCanonical": "Smite Grineer"
            }
          },
          {
            "type": "official-drop",
            "sourceCanonical": "Demolisher Kuva Guardian",
            "chance": 0.0375,
            "quantity": 1,
            "rarity": "Uncommon",
            "reviewStatus": "draft",
            "provenance": {
              "source": "warframe-items",
              "input": "Mods.json",
              "officialUniqueName": "/Lotus/Upgrades/Mods/Melee/WeaponMeleeFactionDamageGrineer",
              "itemCanonical": "Smite Grineer"
            }
          },
          {
            "type": "official-drop",
            "sourceCanonical": "Demolisher Nox",
            "chance": 0.0375,
            "quantity": 1,
            "rarity": "Uncommon",
            "reviewStatus": "draft",
            "provenance": {
              "source": "warframe-items",
              "input": "Mods.json",
              "officialUniqueName": "/Lotus/Upgrades/Mods/Melee/WeaponMeleeFactionDamageGrineer",
              "itemCanonical": "Smite Grineer"
            }
          },
          {
            "type": "official-drop",
            "sourceCanonical": "Mimic",
            "chance": 0.0643,
            "quantity": 1,
            "rarity": "Uncommon",
            "reviewStatus": "draft",
            "provenance": {
              "source": "warframe-items",
              "input": "Mods.json",
              "officialUniqueName": "/Lotus/Upgrades/Mods/Melee/WeaponMeleeFactionDamageGrineer",
              "itemCanonical": "Smite Grineer"
            }
          }
        ]
      },
      "manual": {
        "methods": [],
        "methodRefs": [],
        "overrides": {},
        "reviewStatus": "draft",
        "reviewedBy": []
      }
    }
  }
]
