{
  "id": "currency.proof-fragment",
  "canonical": "Proof Fragment",
  "displayName": "数学证明片段",
  "kind": "resource-token",
  "aliases": [],
  "officialUniqueName": "/Lotus/Types/Items/MiscItems/Beacon",
  "officialSource": "knowledge/generated/official-items.json (DE Languages.bin / Public Export)",
  "localizationStatus": "official-zh",
  "semanticKinds": [
    "currency-token-material"
  ],
  "reviewStatus": "draft",
  "category": "resource-token",
  "boosterEffects": {
    "resourceAmount": "unknown",
    "resourceDropChance": "unknown",
    "exchangeCost": "unaffected",
    "scope": "in-mission-pickups-only",
    "evidence": []
  }
}
