[
  {
    "id": "knowledge.acquisition.mod.icy-avalanche-23f63014",
    "kind": "knowledge",
    "module": "acquisition",
    "title": "冰冷雪崩",
    "subject": {
      "canonical": "Icy Avalanche",
      "displayName": "冰冷雪崩",
      "category": "mod",
      "categoryRefs": [
        "syndicatemod",
        "warframemod",
        "standardmod"
      ]
    },
    "officialUniqueName": "/Lotus/Powersuits/Frost/AvalancheAugmentCard",
    "maxRank": 3,
    "effectDetails": [
      "雪崩强化：用冰衣覆盖经验共享范围内的友军，每次命中敌人时为友军提供 60 超宏防护。每次命中敌人增加相当于护甲值 20% 的超宏防护。"
    ],
    "rarity": "Rare",
    "polarity": "zenurik",
    "tradable": true,
    "prerequisites": [],
    "tips": [],
    "tipKeywords": [
      "本质机制",
      "具体计算公式",
      "加成层级",
      "与同类效果的叠加方式",
      "适用限制"
    ],
    "methodRefs": [],
    "acquisitionStatus": "complete",
    "sources": [
      {
        "url": "https://wiki.warframe.com/w/Icy_Avalanche",
        "label": "Warframe Wiki - Icy Avalanche"
      }
    ],
    "gameVersion": "warframe-items@1.1269.87",
    "updatedAt": "2026-07-22",
    "reviewStatus": "approved",
    "reviewedBy": [
      "official-sync:syndicate-exchange",
      "local-wiki-cross-page-sync"
    ],
    "tags": [
      "acquisition",
      "mod",
      "standard-mod",
      "warframe-mod"
    ],
    "generator": {
      "name": "sync-mods",
      "version": 4
    },
    "modAcquisition": {
      "generated": {
        "identity": {
          "officialUniqueName": "/Lotus/Powersuits/Frost/AvalancheAugmentCard",
          "canonical": "Icy Avalanche",
          "displayName": "冰冷雪崩",
          "maxRank": 3,
          "variant": "standard",
          "typeFolder": "warframe"
        },
        "wiki": {
          "wiki": {
            "pageTitle": "Icy Avalanche",
            "pageId": 1090033,
            "revisionId": 2789395,
            "pageTimestamp": "2026-06-26T16:52:40Z",
            "compiledAt": "2026-07-22T18:16:58.416Z",
            "sourceDatabase": {
              "sha256": "861480127CC518FC3CCA9B28334AEEC16AB8AEA383D08EA5D3B55B701DA475B9",
              "size": 2322874368
            }
          },
          "methods": [
            {
              "type": "syndicate-exchange-group",
              "factionIds": [
                "faction.cephalon-suda",
                "faction.steel-meridian"
              ],
              "standing": 25000,
              "rankRequirement": "max",
              "chance": null,
              "quantity": 1,
              "availability": "guaranteed-when-requirements-met",
              "reviewStatus": "draft",
              "provenance": {
                "source": "local-wiki-sqlite",
                "pageTitle": "Icy Avalanche",
                "pageId": 1090033,
                "revisionId": 2789395,
                "section": "Acquisition",
                "excerpt": "This mod can be acquired by attaining the rank of General under Steel Meridian , or the rank of Genius under Cephalon Suda , and spending 25,000 Standing 25,000 to purchase."
              }
            }
          ],
          "evidence": [
            {
              "type": "acquisition-prose",
              "reviewStatus": "draft",
              "provenance": {
                "source": "local-wiki-sqlite",
                "pageTitle": "Icy Avalanche",
                "pageId": 1090033,
                "revisionId": 2789395,
                "section": "Acquisition",
                "excerpt": "This mod can be acquired by attaining the rank of General under Steel Meridian , or the rank of Genius under Cephalon Suda , and spending 25,000 Standing 25,000 to purchase."
              }
            }
          ],
          "mechanicsEvidence": {
            "status": "draft",
            "notes": [
              {
                "reviewStatus": "draft",
                "provenance": {
                  "source": "local-wiki-sqlite",
                  "pageTitle": "Icy Avalanche",
                  "pageId": 1090033,
                  "revisionId": 2789395,
                  "section": "Notes",
                  "excerpt": "Overguard granted by Icy Avalanche has a cap of 15,000 ."
                }
              },
              {
                "reviewStatus": "draft",
                "provenance": {
                  "source": "local-wiki-sqlite",
                  "pageTitle": "Icy Avalanche",
                  "pageId": 1090033,
                  "revisionId": 2789395,
                  "section": "Notes",
                  "excerpt": "Overguard per enemy is calculated before Frost's Passive, Fortifying Freeze, is applied."
                }
              },
              {
                "reviewStatus": "draft",
                "provenance": {
                  "source": "local-wiki-sqlite",
                  "pageTitle": "Icy Avalanche",
                  "pageId": 1090033,
                  "revisionId": 2789395,
                  "section": "Notes",
                  "excerpt": "Overguard from armor granted per enemy is only gained once per enemy . Subsequent casts on the same enemy will not grant the armor portion of Overguard. Because of this, Fortifying Freeze will only benefit Overguard generation if new enemies are frozen while the armor persists from the previous cast."
                }
              },
              {
                "reviewStatus": "draft",
                "provenance": {
                  "source": "local-wiki-sqlite",
                  "pageTitle": "Icy Avalanche",
                  "pageId": 1090033,
                  "revisionId": 2789395,
                  "section": "Notes",
                  "excerpt": "Enemies still frozen by a previous casting of Avalanche will still grant the 60 Overguard per enemy hit on subsequent casts."
                }
              },
              {
                "reviewStatus": "draft",
                "provenance": {
                  "source": "local-wiki-sqlite",
                  "pageTitle": "Icy Avalanche",
                  "pageId": 1090033,
                  "revisionId": 2789395,
                  "section": "Notes",
                  "excerpt": "The equation for Overguard is:"
                }
              },
              {
                "reviewStatus": "draft",
                "provenance": {
                  "source": "local-wiki-sqlite",
                  "pageTitle": "Icy Avalanche",
                  "pageId": 1090033,
                  "revisionId": 2789395,
                  "section": "Notes",
                  "excerpt": "(60 × Ability Strength × Enemies affected by Avalanche) + (Armor × 20% × Ability Strength × Enemies affected by Avalanche)"
                }
              },
              {
                "reviewStatus": "draft",
                "provenance": {
                  "source": "local-wiki-sqlite",
                  "pageTitle": "Icy Avalanche",
                  "pageId": 1090033,
                  "revisionId": 2789395,
                  "section": "Notes",
                  "excerpt": "For example with 130% Ability Strength, 500 Armor and 10 enemies the equation becomes:"
                }
              },
              {
                "reviewStatus": "draft",
                "provenance": {
                  "source": "local-wiki-sqlite",
                  "pageTitle": "Icy Avalanche",
                  "pageId": 1090033,
                  "revisionId": 2789395,
                  "section": "Notes",
                  "excerpt": "(60 × 1.3 × 10) + (500 × 0.2 × 1.3 × 10) = 2,080"
                }
              },
              {
                "reviewStatus": "draft",
                "provenance": {
                  "source": "local-wiki-sqlite",
                  "pageTitle": "Icy Avalanche",
                  "pageId": 1090033,
                  "revisionId": 2789395,
                  "section": "Notes",
                  "excerpt": "On repeat casts against enemies who have been hit by Avalanche before it becomes:"
                }
              },
              {
                "reviewStatus": "draft",
                "provenance": {
                  "source": "local-wiki-sqlite",
                  "pageTitle": "Icy Avalanche",
                  "pageId": 1090033,
                  "revisionId": 2789395,
                  "section": "Notes",
                  "excerpt": "(60 × Ability Strength × Enemies affected by Avalanche)"
                }
              },
              {
                "reviewStatus": "draft",
                "provenance": {
                  "source": "local-wiki-sqlite",
                  "pageTitle": "Icy Avalanche",
                  "pageId": 1090033,
                  "revisionId": 2789395,
                  "section": "Notes",
                  "excerpt": "For example with 130% Ability Strength, 500 Armor and 10 enemies who have already been affected by Avalanche the equation becomes:"
                }
              },
              {
                "reviewStatus": "draft",
                "provenance": {
                  "source": "local-wiki-sqlite",
                  "pageTitle": "Icy Avalanche",
                  "pageId": 1090033,
                  "revisionId": 2789395,
                  "section": "Notes",
                  "excerpt": "(60 × 1.3 × 10) = 780"
                }
              }
            ],
            "usage": []
          },
          "unresolvedEntities": [],
          "status": "complete"
        },
        "officialDrops": []
      },
      "manual": {
        "methods": [],
        "methodRefs": [],
        "overrides": {},
        "reviewStatus": "approved",
        "reviewedBy": [
          "official-sync:syndicate-exchange",
          "local-wiki-cross-page-sync"
        ]
      }
    }
  }
]
