{
  "id": "knowledge.acquisition.consumable.omni-ammo-box-76bbbd27",
  "kind": "knowledge",
  "module": "acquisition",
  "title": "Omni Ammo Box",
  "subject": {
    "canonical": "Omni Ammo Box",
    "displayName": "综合弹药箱",
    "category": "consumable",
    "officialUniqueName": "/Lotus/Types/Restoratives/SelfOmniAmmo",
    "categoryRefs": [
      "consumable.gear",
      "acquisition.mission"
    ]
  },
  "description": {
    "canonical": "Fully restores all ammo types.",
    "display": "完全补充所有弹药。"
  },
  "classification": {
    "type": "gear",
    "semanticKinds": [
      "droppable",
      "gear"
    ]
  },
  "consumableAcquisition": {
    "generated": {
      "routes": [
        {
          "scope": "item",
          "category": "mission",
          "partRefs": [],
          "variables": {
            "itemName": "综合弹药箱"
          },
          "requirements": {
            "type": "none"
          },
          "methods": [
            {
              "type": "mission-reward",
              "scope": "item",
              "partRefs": [],
              "sourceCanonical": "Mercury/Elion (Capture)",
              "sourceDisplayName": "水星/Elion（Capture）",
              "sourceLocalizationStatus": "official-zh",
              "locationId": "mission.elion-solnode12",
              "missionTypeId": "mission-type.capture",
              "chance": 0.0034000000000000002,
              "sourceDropChance": null,
              "conditionalChance": null,
              "rotation": null,
              "stage": null,
              "requirements": {
                "type": "none"
              },
              "reviewStatus": "approved",
              "provenance": {
                "source": "DE Official Drop Tables",
                "section": "Missions"
              }
            },
            {
              "type": "mission-reward",
              "scope": "item",
              "partRefs": [],
              "sourceCanonical": "Venus/Venera (Capture)",
              "sourceDisplayName": "金星/Venera（Capture）",
              "sourceLocalizationStatus": "official-zh",
              "locationId": "mission.venera-solnode107",
              "missionTypeId": "mission-type.capture",
              "chance": 0.0034000000000000002,
              "sourceDropChance": null,
              "conditionalChance": null,
              "rotation": null,
              "stage": null,
              "requirements": {
                "type": "none"
              },
              "reviewStatus": "approved",
              "provenance": {
                "source": "DE Official Drop Tables",
                "section": "Missions"
              }
            },
            {
              "type": "mission-reward",
              "scope": "item",
              "partRefs": [],
              "sourceCanonical": "Earth/Mantle (Capture)",
              "sourceDisplayName": "地球/Mantle（Capture）",
              "sourceLocalizationStatus": "official-zh",
              "locationId": "mission.mantle-solnode63",
              "missionTypeId": "mission-type.capture",
              "chance": 0.0034000000000000002,
              "sourceDropChance": null,
              "conditionalChance": null,
              "rotation": null,
              "stage": null,
              "requirements": {
                "type": "none"
              },
              "reviewStatus": "approved",
              "provenance": {
                "source": "DE Official Drop Tables",
                "section": "Missions"
              }
            },
            {
              "type": "mission-reward",
              "scope": "item",
              "partRefs": [],
              "sourceCanonical": "Mars/Ara (Capture)",
              "sourceDisplayName": "火星/Ara（Capture）",
              "sourceLocalizationStatus": "official-zh",
              "locationId": "mission.ara-solnode45",
              "missionTypeId": "mission-type.capture",
              "chance": 0.0034000000000000002,
              "sourceDropChance": null,
              "conditionalChance": null,
              "rotation": null,
              "stage": null,
              "requirements": {
                "type": "none"
              },
              "reviewStatus": "approved",
              "provenance": {
                "source": "DE Official Drop Tables",
                "section": "Missions"
              }
            },
            {
              "type": "mission-reward",
              "scope": "item",
              "partRefs": [],
              "sourceCanonical": "Jupiter/Ananke (Capture)",
              "sourceDisplayName": "木星/Ananke（Capture）",
              "sourceLocalizationStatus": "official-zh",
              "locationId": "mission.ananke-solnode73",
              "missionTypeId": "mission-type.capture",
              "chance": 0.0034000000000000002,
              "sourceDropChance": null,
              "conditionalChance": null,
              "rotation": null,
              "stage": null,
              "requirements": {
                "type": "none"
              },
              "reviewStatus": "approved",
              "provenance": {
                "source": "DE Official Drop Tables",
                "section": "Missions"
              }
            },
            {
              "type": "mission-reward",
              "scope": "item",
              "partRefs": [],
              "sourceCanonical": "Saturn/Cassini (Capture)",
              "sourceDisplayName": "土星/Cassini（Capture）",
              "sourceLocalizationStatus": "official-zh",
              "locationId": "mission.cassini-solnode70",
              "missionTypeId": "mission-type.capture",
              "chance": 0.0034000000000000002,
              "sourceDropChance": null,
              "conditionalChance": null,
              "rotation": null,
              "stage": null,
              "requirements": {
                "type": "none"
              },
              "reviewStatus": "approved",
              "provenance": {
                "source": "DE Official Drop Tables",
                "section": "Missions"
              }
            },
            {
              "type": "mission-reward",
              "scope": "item",
              "partRefs": [],
              "sourceCanonical": "Uranus/Ariel (Capture)",
              "sourceDisplayName": "天王星/Ariel（Capture）",
              "sourceLocalizationStatus": "official-zh",
              "locationId": "mission.ariel-solnode33",
              "missionTypeId": "mission-type.capture",
              "chance": 0.0034000000000000002,
              "sourceDropChance": null,
              "conditionalChance": null,
              "rotation": null,
              "stage": null,
              "requirements": {
                "type": "none"
              },
              "reviewStatus": "approved",
              "provenance": {
                "source": "DE Official Drop Tables",
                "section": "Missions"
              }
            },
            {
              "type": "mission-reward",
              "scope": "item",
              "partRefs": [],
              "sourceCanonical": "Neptune/Galatea (Capture)",
              "sourceDisplayName": "海王星/Galatea（Capture）",
              "sourceLocalizationStatus": "official-zh",
              "locationId": "mission.galatea-solnode1",
              "missionTypeId": "mission-type.capture",
              "chance": 0.0034000000000000002,
              "sourceDropChance": null,
              "conditionalChance": null,
              "rotation": null,
              "stage": null,
              "requirements": {
                "type": "none"
              },
              "reviewStatus": "approved",
              "provenance": {
                "source": "DE Official Drop Tables",
                "section": "Missions"
              }
            },
            {
              "type": "mission-reward",
              "scope": "item",
              "partRefs": [],
              "sourceCanonical": "Pluto/Hydra (Capture)",
              "sourceDisplayName": "冥王星/Hydra（Capture）",
              "sourceLocalizationStatus": "official-zh",
              "locationId": "mission.hydra-solnode76",
              "missionTypeId": "mission-type.capture",
              "chance": 0.0034000000000000002,
              "sourceDropChance": null,
              "conditionalChance": null,
              "rotation": null,
              "stage": null,
              "requirements": {
                "type": "none"
              },
              "reviewStatus": "approved",
              "provenance": {
                "source": "DE Official Drop Tables",
                "section": "Missions"
              }
            },
            {
              "type": "mission-reward",
              "scope": "item",
              "partRefs": [],
              "sourceCanonical": "Ceres/Lex (Capture)",
              "sourceDisplayName": "谷神星/Lex（Capture）",
              "sourceLocalizationStatus": "official-zh",
              "locationId": "mission.lex-solnode139",
              "missionTypeId": "mission-type.capture",
              "chance": 0.0034000000000000002,
              "sourceDropChance": null,
              "conditionalChance": null,
              "rotation": null,
              "stage": null,
              "requirements": {
                "type": "none"
              },
              "reviewStatus": "approved",
              "provenance": {
                "source": "DE Official Drop Tables",
                "section": "Missions"
              }
            },
            {
              "type": "mission-reward",
              "scope": "item",
              "partRefs": [],
              "sourceCanonical": "Eris/Isos (Capture)",
              "sourceDisplayName": "阋神星/Isos（Capture）",
              "sourceLocalizationStatus": "official-zh",
              "locationId": "mission.isos-solnode162",
              "missionTypeId": "mission-type.capture",
              "chance": 0.0034000000000000002,
              "sourceDropChance": null,
              "conditionalChance": null,
              "rotation": null,
              "stage": null,
              "requirements": {
                "type": "none"
              },
              "reviewStatus": "approved",
              "provenance": {
                "source": "DE Official Drop Tables",
                "section": "Missions"
              }
            },
            {
              "type": "mission-reward",
              "scope": "item",
              "partRefs": [],
              "sourceCanonical": "Europa/Abaddon (Capture)",
              "sourceDisplayName": "欧罗巴/Abaddon（Capture）",
              "sourceLocalizationStatus": "official-zh",
              "locationId": "mission.abaddon-solnode203",
              "missionTypeId": "mission-type.capture",
              "chance": 0.0034000000000000002,
              "sourceDropChance": null,
              "conditionalChance": null,
              "rotation": null,
              "stage": null,
              "requirements": {
                "type": "none"
              },
              "reviewStatus": "approved",
              "provenance": {
                "source": "DE Official Drop Tables",
                "section": "Missions"
              }
            },
            {
              "type": "mission-reward",
              "scope": "item",
              "partRefs": [],
              "sourceCanonical": "Phobos/Skyresh (Capture)",
              "sourceDisplayName": "火卫一/Skyresh（Capture）",
              "sourceLocalizationStatus": "official-zh",
              "locationId": "mission.skyresh-settlementnode2",
              "missionTypeId": "mission-type.capture",
              "chance": 0.0034000000000000002,
              "sourceDropChance": null,
              "conditionalChance": null,
              "rotation": null,
              "stage": null,
              "requirements": {
                "type": "none"
              },
              "reviewStatus": "approved",
              "provenance": {
                "source": "DE Official Drop Tables",
                "section": "Missions"
              }
            },
            {
              "type": "mission-reward",
              "scope": "item",
              "partRefs": [],
              "sourceCanonical": "Lua/Copernicus (Capture)",
              "sourceDisplayName": "月球/Copernicus（Capture）",
              "sourceLocalizationStatus": "official-zh",
              "locationId": "mission.copernicus-solnode304",
              "missionTypeId": "mission-type.capture",
              "chance": 0.0034000000000000002,
              "sourceDropChance": null,
              "conditionalChance": null,
              "rotation": null,
              "stage": null,
              "requirements": {
                "type": "none"
              },
              "reviewStatus": "approved",
              "provenance": {
                "source": "DE Official Drop Tables",
                "section": "Missions"
              }
            }
          ],
          "status": "complete",
          "evidence": [
            {
              "type": "mission-reward",
              "scope": "item",
              "partRefs": [],
              "sourceCanonical": "Event: Mars/Quirinus (Capture)",
              "sourceDisplayName": "",
              "sourceLocalizationStatus": "official-zh-unavailable",
              "locationId": null,
              "missionTypeId": "mission-type.capture",
              "chance": 0.0034000000000000002,
              "sourceDropChance": null,
              "conditionalChance": null,
              "rotation": null,
              "stage": null,
              "requirements": {
                "type": "none"
              },
              "reviewStatus": "review-required",
              "provenance": {
                "source": "DE Official Drop Tables",
                "section": "Missions"
              }
            },
            {
              "type": "mission-reward",
              "scope": "item",
              "partRefs": [],
              "sourceCanonical": "Event: Saturn/Phoebe (Capture)",
              "sourceDisplayName": "",
              "sourceLocalizationStatus": "official-zh-unavailable",
              "locationId": null,
              "missionTypeId": "mission-type.capture",
              "chance": 0.0034000000000000002,
              "sourceDropChance": null,
              "conditionalChance": null,
              "rotation": null,
              "stage": null,
              "requirements": {
                "type": "none"
              },
              "reviewStatus": "review-required",
              "provenance": {
                "source": "DE Official Drop Tables",
                "section": "Missions"
              }
            },
            {
              "type": "mission-reward",
              "scope": "item",
              "partRefs": [],
              "sourceCanonical": "Event: Uranus/Trinculo (Capture)",
              "sourceDisplayName": "",
              "sourceLocalizationStatus": "official-zh-unavailable",
              "locationId": null,
              "missionTypeId": "mission-type.capture",
              "chance": 0.0034000000000000002,
              "sourceDropChance": null,
              "conditionalChance": null,
              "rotation": null,
              "stage": null,
              "requirements": {
                "type": "none"
              },
              "reviewStatus": "review-required",
              "provenance": {
                "source": "DE Official Drop Tables",
                "section": "Missions"
              }
            },
            {
              "type": "mission-reward",
              "scope": "item",
              "partRefs": [],
              "sourceCanonical": "Event: Pluto/Corb (Capture)",
              "sourceDisplayName": "",
              "sourceLocalizationStatus": "official-zh-unavailable",
              "locationId": null,
              "missionTypeId": "mission-type.capture",
              "chance": 0.0034000000000000002,
              "sourceDropChance": null,
              "conditionalChance": null,
              "rotation": null,
              "stage": null,
              "requirements": {
                "type": "none"
              },
              "reviewStatus": "review-required",
              "provenance": {
                "source": "DE Official Drop Tables",
                "section": "Missions"
              }
            },
            {
              "type": "mission-reward",
              "scope": "item",
              "partRefs": [],
              "sourceCanonical": "Event: Eris/Cosis (Capture)",
              "sourceDisplayName": "",
              "sourceLocalizationStatus": "official-zh-unavailable",
              "locationId": null,
              "missionTypeId": "mission-type.capture",
              "chance": 0.0034000000000000002,
              "sourceDropChance": null,
              "conditionalChance": null,
              "rotation": null,
              "stage": null,
              "requirements": {
                "type": "none"
              },
              "reviewStatus": "review-required",
              "provenance": {
                "source": "DE Official Drop Tables",
                "section": "Missions"
              }
            },
            {
              "type": "mission-reward",
              "scope": "item",
              "partRefs": [],
              "sourceCanonical": "Event: Europa/Cryotic Front (Capture)",
              "sourceDisplayName": "",
              "sourceLocalizationStatus": "official-zh-unavailable",
              "locationId": null,
              "missionTypeId": "mission-type.capture",
              "chance": 0.0034000000000000002,
              "sourceDropChance": null,
              "conditionalChance": null,
              "rotation": null,
              "stage": null,
              "requirements": {
                "type": "none"
              },
              "reviewStatus": "review-required",
              "provenance": {
                "source": "DE Official Drop Tables",
                "section": "Missions"
              }
            },
            {
              "type": "mission-reward",
              "scope": "item",
              "partRefs": [],
              "sourceCanonical": "Event: Europa/Beleth (Capture)",
              "sourceDisplayName": "",
              "sourceLocalizationStatus": "official-zh-unavailable",
              "locationId": null,
              "missionTypeId": "mission-type.capture",
              "chance": 0.0034000000000000002,
              "sourceDropChance": null,
              "conditionalChance": null,
              "rotation": null,
              "stage": null,
              "requirements": {
                "type": "none"
              },
              "reviewStatus": "review-required",
              "provenance": {
                "source": "DE Official Drop Tables",
                "section": "Missions"
              }
            },
            {
              "type": "mission-reward",
              "scope": "item",
              "partRefs": [],
              "sourceCanonical": "Event: Phobos/Limtoc (Capture)",
              "sourceDisplayName": "",
              "sourceLocalizationStatus": "official-zh-unavailable",
              "locationId": null,
              "missionTypeId": "mission-type.capture",
              "chance": 0.0034000000000000002,
              "sourceDropChance": null,
              "conditionalChance": null,
              "rotation": null,
              "stage": null,
              "requirements": {
                "type": "none"
              },
              "reviewStatus": "review-required",
              "provenance": {
                "source": "DE Official Drop Tables",
                "section": "Missions"
              }
            },
            {
              "type": "mission-reward",
              "scope": "item",
              "partRefs": [],
              "sourceCanonical": "Event: Phobos/Todd (Capture)",
              "sourceDisplayName": "",
              "sourceLocalizationStatus": "official-zh-unavailable",
              "locationId": null,
              "missionTypeId": "mission-type.capture",
              "chance": 0.0034000000000000002,
              "sourceDropChance": null,
              "conditionalChance": null,
              "rotation": null,
              "stage": null,
              "requirements": {
                "type": "none"
              },
              "reviewStatus": "review-required",
              "provenance": {
                "source": "DE Official Drop Tables",
                "section": "Missions"
              }
            },
            {
              "scope": "item",
              "sourceCanonical": "Ceres/Lex (Capture)",
              "chance": 0.0034,
              "requirements": {
                "type": "none"
              },
              "provenance": {
                "source": "installed-warframe-items",
                "field": "drops"
              },
              "type": "enemy-drop",
              "sourceDisplayName": "",
              "reviewStatus": "review-required"
            },
            {
              "scope": "item",
              "sourceCanonical": "Earth/Mantle (Capture)",
              "chance": 0.0034,
              "requirements": {
                "type": "none"
              },
              "provenance": {
                "source": "installed-warframe-items",
                "field": "drops"
              },
              "type": "enemy-drop",
              "sourceDisplayName": "",
              "reviewStatus": "review-required"
            },
            {
              "scope": "item",
              "sourceCanonical": "Eris/Cosis (Capture)",
              "chance": 0.0034,
              "requirements": {
                "type": "none"
              },
              "provenance": {
                "source": "installed-warframe-items",
                "field": "drops"
              },
              "type": "enemy-drop",
              "sourceDisplayName": "",
              "reviewStatus": "review-required"
            },
            {
              "scope": "item",
              "sourceCanonical": "Eris/Isos (Capture)",
              "chance": 0.0034,
              "requirements": {
                "type": "none"
              },
              "provenance": {
                "source": "installed-warframe-items",
                "field": "drops"
              },
              "type": "enemy-drop",
              "sourceDisplayName": "",
              "reviewStatus": "review-required"
            },
            {
              "scope": "item",
              "sourceCanonical": "Europa/Abaddon (Capture)",
              "chance": 0.0034,
              "requirements": {
                "type": "none"
              },
              "provenance": {
                "source": "installed-warframe-items",
                "field": "drops"
              },
              "type": "enemy-drop",
              "sourceDisplayName": "",
              "reviewStatus": "review-required"
            },
            {
              "scope": "item",
              "sourceCanonical": "Europa/Beleth (Capture)",
              "chance": 0.0034,
              "requirements": {
                "type": "none"
              },
              "provenance": {
                "source": "installed-warframe-items",
                "field": "drops"
              },
              "type": "enemy-drop",
              "sourceDisplayName": "",
              "reviewStatus": "review-required"
            },
            {
              "scope": "item",
              "sourceCanonical": "Europa/Cryotic Front (Capture)",
              "chance": 0.0034,
              "requirements": {
                "type": "none"
              },
              "provenance": {
                "source": "installed-warframe-items",
                "field": "drops"
              },
              "type": "enemy-drop",
              "sourceDisplayName": "",
              "reviewStatus": "review-required"
            },
            {
              "scope": "item",
              "sourceCanonical": "Jupiter/Ananke (Capture)",
              "chance": 0.0034,
              "requirements": {
                "type": "none"
              },
              "provenance": {
                "source": "installed-warframe-items",
                "field": "drops"
              },
              "type": "enemy-drop",
              "sourceDisplayName": "",
              "reviewStatus": "review-required"
            },
            {
              "scope": "item",
              "sourceCanonical": "Lua/Copernicus (Capture)",
              "chance": 0.0034,
              "requirements": {
                "type": "none"
              },
              "provenance": {
                "source": "installed-warframe-items",
                "field": "drops"
              },
              "type": "enemy-drop",
              "sourceDisplayName": "",
              "reviewStatus": "review-required"
            },
            {
              "scope": "item",
              "sourceCanonical": "Mars/Ara (Capture)",
              "chance": 0.0034,
              "requirements": {
                "type": "none"
              },
              "provenance": {
                "source": "installed-warframe-items",
                "field": "drops"
              },
              "type": "enemy-drop",
              "sourceDisplayName": "",
              "reviewStatus": "review-required"
            },
            {
              "scope": "item",
              "sourceCanonical": "Mars/Quirinus (Capture)",
              "chance": 0.0034,
              "requirements": {
                "type": "none"
              },
              "provenance": {
                "source": "installed-warframe-items",
                "field": "drops"
              },
              "type": "enemy-drop",
              "sourceDisplayName": "",
              "reviewStatus": "review-required"
            },
            {
              "scope": "item",
              "sourceCanonical": "Mercury/Elion (Capture)",
              "chance": 0.0034,
              "requirements": {
                "type": "none"
              },
              "provenance": {
                "source": "installed-warframe-items",
                "field": "drops"
              },
              "type": "enemy-drop",
              "sourceDisplayName": "",
              "reviewStatus": "review-required"
            },
            {
              "scope": "item",
              "sourceCanonical": "Neptune/Galatea (Capture)",
              "chance": 0.0034,
              "requirements": {
                "type": "none"
              },
              "provenance": {
                "source": "installed-warframe-items",
                "field": "drops"
              },
              "type": "enemy-drop",
              "sourceDisplayName": "",
              "reviewStatus": "review-required"
            },
            {
              "scope": "item",
              "sourceCanonical": "Phobos/Limtoc (Capture)",
              "chance": 0.0034,
              "requirements": {
                "type": "none"
              },
              "provenance": {
                "source": "installed-warframe-items",
                "field": "drops"
              },
              "type": "enemy-drop",
              "sourceDisplayName": "",
              "reviewStatus": "review-required"
            },
            {
              "scope": "item",
              "sourceCanonical": "Phobos/Skyresh (Capture)",
              "chance": 0.0034,
              "requirements": {
                "type": "none"
              },
              "provenance": {
                "source": "installed-warframe-items",
                "field": "drops"
              },
              "type": "enemy-drop",
              "sourceDisplayName": "",
              "reviewStatus": "review-required"
            },
            {
              "scope": "item",
              "sourceCanonical": "Phobos/Todd (Capture)",
              "chance": 0.0034,
              "requirements": {
                "type": "none"
              },
              "provenance": {
                "source": "installed-warframe-items",
                "field": "drops"
              },
              "type": "enemy-drop",
              "sourceDisplayName": "",
              "reviewStatus": "review-required"
            },
            {
              "scope": "item",
              "sourceCanonical": "Pluto/Corb (Capture)",
              "chance": 0.0034,
              "requirements": {
                "type": "none"
              },
              "provenance": {
                "source": "installed-warframe-items",
                "field": "drops"
              },
              "type": "enemy-drop",
              "sourceDisplayName": "",
              "reviewStatus": "review-required"
            },
            {
              "scope": "item",
              "sourceCanonical": "Pluto/Hydra (Capture)",
              "chance": 0.0034,
              "requirements": {
                "type": "none"
              },
              "provenance": {
                "source": "installed-warframe-items",
                "field": "drops"
              },
              "type": "enemy-drop",
              "sourceDisplayName": "",
              "reviewStatus": "review-required"
            },
            {
              "scope": "item",
              "sourceCanonical": "Saturn/Cassini (Capture)",
              "chance": 0.0034,
              "requirements": {
                "type": "none"
              },
              "provenance": {
                "source": "installed-warframe-items",
                "field": "drops"
              },
              "type": "enemy-drop",
              "sourceDisplayName": "",
              "reviewStatus": "review-required"
            },
            {
              "scope": "item",
              "sourceCanonical": "Saturn/Phoebe (Capture)",
              "chance": 0.0034,
              "requirements": {
                "type": "none"
              },
              "provenance": {
                "source": "installed-warframe-items",
                "field": "drops"
              },
              "type": "enemy-drop",
              "sourceDisplayName": "",
              "reviewStatus": "review-required"
            },
            {
              "scope": "item",
              "sourceCanonical": "Uranus/Ariel (Capture)",
              "chance": 0.0034,
              "requirements": {
                "type": "none"
              },
              "provenance": {
                "source": "installed-warframe-items",
                "field": "drops"
              },
              "type": "enemy-drop",
              "sourceDisplayName": "",
              "reviewStatus": "review-required"
            },
            {
              "scope": "item",
              "sourceCanonical": "Uranus/Trinculo (Capture)",
              "chance": 0.0034,
              "requirements": {
                "type": "none"
              },
              "provenance": {
                "source": "installed-warframe-items",
                "field": "drops"
              },
              "type": "enemy-drop",
              "sourceDisplayName": "",
              "reviewStatus": "review-required"
            },
            {
              "scope": "item",
              "sourceCanonical": "Venus/Venera (Capture)",
              "chance": 0.0034,
              "requirements": {
                "type": "none"
              },
              "provenance": {
                "source": "installed-warframe-items",
                "field": "drops"
              },
              "type": "enemy-drop",
              "sourceDisplayName": "",
              "reviewStatus": "review-required"
            }
          ]
        }
      ],
      "recipes": []
    },
    "manual": {
      "tips": [],
      "tipKeywords": [],
      "methods": [],
      "reviewedBy": []
    }
  },
  "recipes": [],
  "prerequisites": [],
  "methodRefs": [],
  "summary": "完全补充所有弹药。",
  "sources": [
    {
      "url": "https://github.com/WFCD/warframe-items",
      "label": "warframe-items / DE Public Export"
    },
    {
      "url": "https://www.warframe.com/droptables",
      "label": "DE Official Drop Tables"
    }
  ],
  "gameVersion": "current",
  "updatedAt": "2026-07-16",
  "reviewStatus": "approved",
  "status": "complete",
  "coverage": {
    "identity": true,
    "acquisition": true,
    "blueprint": false,
    "crafting": true
  }
}
